{"api_version": "2022-08-31", "model_id": "bc2-narrative", "content": "Cleveland Division of Police\nDetail\nPrint Date/Time: Login ID: Case Number:\n10/12/2018 10:27 mastroip 2017-00253217\nORI Number:\nSubject # 1-Suspect\nPrimary: No\nSuspect Type:\nArrested\nName: Payne, Ronald\nRace:\nWhite\nSex:\nMale\nAddress: 19310 MUSKOKA AVE CLEVELAND OH 44119\nPrimary Phone:\n(216)501-8124\nHeight: Eyes: SSN:\n5ft 11 in Blue\nWeight: Hair: DVL #:\n250.0 lbs. Blonde or Strawberry 1 - MTR V...\nResident Type:\nCity\nResident Status:\nResident\nStatement Type:\nDisposition:\nDate:\nCustody Status:\nRelated Offenses\nGroup/ORI\nCrime Code\nStatute\nDescription\nOHCLP0000\n27120\n623.16\nNo Person Shall Violate,,,,, By Reason Of The\nRace\nCleveland Division of Police OHCLP0000\nDOB:\n10/27/1961\nBuild:\nMedium\nAge:\n55\nState:\nVerbal\nOH\nRelated Weapons\nVictim/Offender Relationship\nNo. Type\nName\nRelationship\n1 Suspect\nPayne,Ronald\nNeighbor\nTransported By:\nExtent of Injury:\nHospital:\nDomestic Violence: Condition:\nDomestic Violence Referrals: Medical Treatment:\nFederal Agencies Involved:\nInjury Types\nModus Operandi\nMissing Person Information\nPage: 3 of 7 Page: 3 of 6\nCLEVELAND\nPOLICE\nYou created this PDF from an application that is not licensed to print to novaPDF printer (http://www.novapdf.com)", "languages": [], "pages": [{"page_number": 3, "angle": null, "width": 8.5, "height": 11.0, "unit": "inch", "lines": [{"content": "Cleveland Division of Police", "polygon": [{"x": 2.6277, "y": 0.8931}, {"x": 5.8769, "y": 0.8931}, {"x": 5.8769, "y": 1.0842}, {"x": 2.6277, "y": 1.0842}], "spans": [{"offset": 0, "length": 28}]}, {"content": "Detail", "polygon": [{"x": 3.9535, "y": 1.2567}, {"x": 4.55, "y": 1.2567}, {"x": 4.55, "y": 1.4289}, {"x": 3.9535, "y": 1.4289}], "spans": [{"offset": 29, "length": 6}]}, {"content": "Print Date/Time:", "polygon": [{"x": 0.6089, "y": 1.6961}, {"x": 1.5274, "y": 1.6961}, {"x": 1.5274, "y": 1.7898}, {"x": 0.6089, "y": 1.7898}], "spans": [{"offset": 36, "length": 16}]}, {"content": "Login ID:", "polygon": [{"x": 0.6093, "y": 1.8446}, {"x": 1.1194, "y": 1.8446}, {"x": 1.1194, "y": 1.961}, {"x": 0.6093, "y": 1.961}], "spans": [{"offset": 53, "length": 9}]}, {"content": "Case Number:", "polygon": [{"x": 0.6056, "y": 1.9902}, {"x": 1.4226, "y": 1.9902}, {"x": 1.4226, "y": 2.0861}, {"x": 0.6056, "y": 2.0861}], "spans": [{"offset": 63, "length": 12}]}, {"content": "10/12/2018 10:27", "polygon": [{"x": 1.6917, "y": 1.6964}, {"x": 2.628, "y": 1.6964}, {"x": 2.628, "y": 1.789}, {"x": 1.6917, "y": 1.789}], "spans": [{"offset": 76, "length": 16}]}, {"content": "mastroip", "polygon": [{"x": 1.6864, "y": 1.8454}, {"x": 2.1478, "y": 1.8454}, {"x": 2.1478, "y": 1.9593}, {"x": 1.6864, "y": 1.9593}], "spans": [{"offset": 93, "length": 8}]}, {"content": "2017-00253217", "polygon": [{"x": 1.6815, "y": 1.9905}, {"x": 2.5329, "y": 1.9905}, {"x": 2.5329, "y": 2.0866}, {"x": 1.6815, "y": 2.0866}], "spans": [{"offset": 102, "length": 13}]}, {"content": "ORI Number:", "polygon": [{"x": 5.0398, "y": 1.8432}, {"x": 5.7819, "y": 1.8432}, {"x": 5.7819, "y": 1.9391}, {"x": 5.0398, "y": 1.9391}], "spans": [{"offset": 116, "length": 11}]}, {"content": "Subject #", "polygon": [{"x": 0.6041, "y": 2.2843}, {"x": 1.1456, "y": 2.2843}, {"x": 1.1456, "y": 2.403}, {"x": 0.6041, "y": 2.403}], "spans": [{"offset": 128, "length": 9}]}, {"content": "1-Suspect", "polygon": [{"x": 1.4416, "y": 2.2833}, {"x": 1.9483, "y": 2.2833}, {"x": 1.9483, "y": 2.3842}, {"x": 1.4416, "y": 2.3842}], "spans": [{"offset": 138, "length": 9}]}, {"content": "Primary:", "polygon": [{"x": 0.6077, "y": 2.4807}, {"x": 1.0299, "y": 2.4807}, {"x": 1.0299, "y": 2.5817}, {"x": 0.6077, "y": 2.5817}], "spans": [{"offset": 148, "length": 8}]}, {"content": "No", "polygon": [{"x": 1.3923, "y": 2.4813}, {"x": 1.5181, "y": 2.4813}, {"x": 1.5181, "y": 2.5627}, {"x": 1.3923, "y": 2.5627}], "spans": [{"offset": 157, "length": 2}]}, {"content": "Suspect Type:", "polygon": [{"x": 3.5447, "y": 2.4794}, {"x": 4.2752, "y": 2.4794}, {"x": 4.2752, "y": 2.5817}, {"x": 3.5447, "y": 2.5817}], "spans": [{"offset": 160, "length": 13}]}, {"content": "Arrested", "polygon": [{"x": 5.0605, "y": 2.4813}, {"x": 5.4622, "y": 2.4813}, {"x": 5.4622, "y": 2.5627}, {"x": 5.0605, "y": 2.5627}], "spans": [{"offset": 174, "length": 8}]}, {"content": "Name:", "polygon": [{"x": 0.6077, "y": 2.6277}, {"x": 0.922, "y": 2.6277}, {"x": 0.922, "y": 2.7071}, {"x": 0.6077, "y": 2.7071}], "spans": [{"offset": 183, "length": 5}]}, {"content": "Payne, Ronald", "polygon": [{"x": 1.3923, "y": 2.6284}, {"x": 2.0897, "y": 2.6284}, {"x": 2.0897, "y": 2.7292}, {"x": 1.3923, "y": 2.7292}], "spans": [{"offset": 189, "length": 13}]}, {"content": "Race:", "polygon": [{"x": 3.5488, "y": 2.6277}, {"x": 3.8286, "y": 2.6277}, {"x": 3.8286, "y": 2.7071}, {"x": 3.5488, "y": 2.7071}], "spans": [{"offset": 203, "length": 5}]}, {"content": "White", "polygon": [{"x": 4.0323, "y": 2.6284}, {"x": 4.3056, "y": 2.6284}, {"x": 4.3056, "y": 2.7072}, {"x": 4.0323, "y": 2.7072}], "spans": [{"offset": 209, "length": 5}]}, {"content": "Sex:", "polygon": [{"x": 4.9173, "y": 2.6264}, {"x": 5.1314, "y": 2.6264}, {"x": 5.1314, "y": 2.7073}, {"x": 4.9173, "y": 2.7073}], "spans": [{"offset": 215, "length": 4}]}, {"content": "Male", "polygon": [{"x": 5.5097, "y": 2.6284}, {"x": 5.7335, "y": 2.6284}, {"x": 5.7335, "y": 2.7071}, {"x": 5.5097, "y": 2.7071}], "spans": [{"offset": 220, "length": 4}]}, {"content": "Address:", "polygon": [{"x": 0.5997, "y": 2.7748}, {"x": 1.0593, "y": 2.7748}, {"x": 1.0593, "y": 2.8541}, {"x": 0.5997, "y": 2.8541}], "spans": [{"offset": 225, "length": 8}]}, {"content": "19310 MUSKOKA AVE", "polygon": [{"x": 1.3958, "y": 2.7731}, {"x": 2.5022, "y": 2.7731}, {"x": 2.5022, "y": 2.8555}, {"x": 1.3958, "y": 2.8555}], "spans": [{"offset": 234, "length": 17}]}, {"content": "CLEVELAND OH 44119", "polygon": [{"x": 1.3877, "y": 2.9211}, {"x": 2.5544, "y": 2.9211}, {"x": 2.5544, "y": 3.0012}, {"x": 1.3877, "y": 3.0012}], "spans": [{"offset": 252, "length": 18}]}, {"content": "Primary Phone:", "polygon": [{"x": 0.6077, "y": 3.1669}, {"x": 1.3928, "y": 3.1669}, {"x": 1.3928, "y": 3.268}, {"x": 0.6077, "y": 3.268}], "spans": [{"offset": 271, "length": 14}]}, {"content": "(216)501-8124", "polygon": [{"x": 1.5866, "y": 3.1644}, {"x": 2.2881, "y": 3.1644}, {"x": 2.2881, "y": 3.2678}, {"x": 1.5866, "y": 3.2678}], "spans": [{"offset": 286, "length": 13}]}, {"content": "Height:", "polygon": [{"x": 3.5488, "y": 2.7748}, {"x": 3.9062, "y": 2.7748}, {"x": 3.9062, "y": 2.8758}, {"x": 3.5488, "y": 2.8758}], "spans": [{"offset": 300, "length": 7}]}, {"content": "Eyes:", "polygon": [{"x": 3.5488, "y": 2.9218}, {"x": 3.8215, "y": 2.9218}, {"x": 3.8215, "y": 3.0229}, {"x": 3.5488, "y": 3.0229}], "spans": [{"offset": 308, "length": 5}]}, {"content": "SSN:", "polygon": [{"x": 3.5447, "y": 3.1657}, {"x": 3.7917, "y": 3.1657}, {"x": 3.7917, "y": 3.2465}, {"x": 3.5447, "y": 3.2465}], "spans": [{"offset": 314, "length": 4}]}, {"content": "5ft 11 in", "polygon": [{"x": 4.0356, "y": 2.7734}, {"x": 4.4105, "y": 2.7734}, {"x": 4.4105, "y": 2.8572}, {"x": 4.0356, "y": 2.8572}], "spans": [{"offset": 319, "length": 9}]}, {"content": "Blue", "polygon": [{"x": 4.039, "y": 2.9225}, {"x": 4.2434, "y": 2.9225}, {"x": 4.2434, "y": 3.0043}, {"x": 4.039, "y": 3.0043}], "spans": [{"offset": 329, "length": 4}]}, {"content": "Weight:", "polygon": [{"x": 4.9137, "y": 2.7748}, {"x": 5.3, "y": 2.7748}, {"x": 5.3, "y": 2.8758}, {"x": 4.9137, "y": 2.8758}], "spans": [{"offset": 334, "length": 7}]}, {"content": "Hair:", "polygon": [{"x": 4.9214, "y": 2.9218}, {"x": 5.1508, "y": 2.9218}, {"x": 5.1508, "y": 3.0012}, {"x": 4.9214, "y": 3.0012}], "spans": [{"offset": 342, "length": 5}]}, {"content": "DVL #:", "polygon": [{"x": 4.9214, "y": 3.1657}, {"x": 5.2463, "y": 3.1657}, {"x": 5.2463, "y": 3.2463}, {"x": 4.9214, "y": 3.2463}], "spans": [{"offset": 348, "length": 6}]}, {"content": "250.0 lbs.", "polygon": [{"x": 5.5046, "y": 2.7737}, {"x": 5.9635, "y": 2.7737}, {"x": 5.9635, "y": 2.8572}, {"x": 5.5046, "y": 2.8572}], "spans": [{"offset": 355, "length": 10}]}, {"content": "Blonde or", "polygon": [{"x": 5.5096, "y": 2.9225}, {"x": 5.9704, "y": 2.9225}, {"x": 5.9704, "y": 3.0039}, {"x": 5.5096, "y": 3.0039}], "spans": [{"offset": 366, "length": 9}]}, {"content": "Strawberry", "polygon": [{"x": 5.5066, "y": 3.0444}, {"x": 6.0219, "y": 3.0444}, {"x": 6.0219, "y": 3.1475}, {"x": 5.5066, "y": 3.1475}], "spans": [{"offset": 376, "length": 10}]}, {"content": "1 - MTR V...", "polygon": [{"x": 5.5395, "y": 3.1915}, {"x": 5.9399, "y": 3.1915}, {"x": 5.9399, "y": 3.2488}, {"x": 5.5395, "y": 3.2488}], "spans": [{"offset": 387, "length": 12}]}, {"content": "Resident Type:", "polygon": [{"x": 0.6077, "y": 3.314}, {"x": 1.3699, "y": 3.314}, {"x": 1.3699, "y": 3.415}, {"x": 0.6077, "y": 3.415}], "spans": [{"offset": 400, "length": 14}]}, {"content": "City", "polygon": [{"x": 1.5838, "y": 3.3133}, {"x": 1.7619, "y": 3.3133}, {"x": 1.7619, "y": 3.4155}, {"x": 1.5838, "y": 3.4155}], "spans": [{"offset": 415, "length": 4}]}, {"content": "Resident Status:", "polygon": [{"x": 3.0096, "y": 3.3127}, {"x": 3.8503, "y": 3.3127}, {"x": 3.8503, "y": 3.394}, {"x": 3.0096, "y": 3.394}], "spans": [{"offset": 420, "length": 16}]}, {"content": "Resident", "polygon": [{"x": 4.0396, "y": 3.3146}, {"x": 4.456, "y": 3.3146}, {"x": 4.456, "y": 3.3961}, {"x": 4.0396, "y": 3.3961}], "spans": [{"offset": 437, "length": 8}]}, {"content": "Statement Type:", "polygon": [{"x": 5.5545, "y": 3.3127}, {"x": 6.3862, "y": 3.3127}, {"x": 6.3862, "y": 3.415}, {"x": 5.5545, "y": 3.415}], "spans": [{"offset": 446, "length": 15}]}, {"content": "Disposition:", "polygon": [{"x": 0.6077, "y": 3.4611}, {"x": 1.2163, "y": 3.4611}, {"x": 1.2163, "y": 3.5606}, {"x": 0.6077, "y": 3.5606}], "spans": [{"offset": 462, "length": 12}]}, {"content": "Date:", "polygon": [{"x": 3.5488, "y": 3.4611}, {"x": 3.8013, "y": 3.4611}, {"x": 3.8013, "y": 3.5411}, {"x": 3.5488, "y": 3.5411}], "spans": [{"offset": 475, "length": 5}]}, {"content": "Custody Status:", "polygon": [{"x": 5.5558, "y": 3.4598}, {"x": 6.3734, "y": 3.4598}, {"x": 6.3734, "y": 3.5621}, {"x": 5.5558, "y": 3.5621}], "spans": [{"offset": 481, "length": 15}]}, {"content": "Related Offenses", "polygon": [{"x": 0.6077, "y": 3.6552}, {"x": 1.4842, "y": 3.6552}, {"x": 1.4842, "y": 3.7372}, {"x": 0.6077, "y": 3.7372}], "spans": [{"offset": 497, "length": 16}]}, {"content": "Group/ORI", "polygon": [{"x": 0.7012, "y": 3.8519}, {"x": 1.2418, "y": 3.8519}, {"x": 1.2418, "y": 3.9528}, {"x": 0.7012, "y": 3.9528}], "spans": [{"offset": 514, "length": 9}]}, {"content": "Crime Code", "polygon": [{"x": 1.7388, "y": 3.8519}, {"x": 2.3421, "y": 3.8519}, {"x": 2.3421, "y": 3.9353}, {"x": 1.7388, "y": 3.9353}], "spans": [{"offset": 524, "length": 10}]}, {"content": "Statute", "polygon": [{"x": 3.4173, "y": 3.8519}, {"x": 3.7782, "y": 3.8519}, {"x": 3.7782, "y": 3.9333}, {"x": 3.4173, "y": 3.9333}], "spans": [{"offset": 535, "length": 7}]}, {"content": "Description", "polygon": [{"x": 5.3952, "y": 3.8532}, {"x": 5.9784, "y": 3.8532}, {"x": 5.9784, "y": 3.9528}, {"x": 5.3952, "y": 3.9528}], "spans": [{"offset": 543, "length": 11}]}, {"content": "OHCLP0000", "polygon": [{"x": 0.85, "y": 4.0286}, {"x": 1.4558, "y": 4.0286}, {"x": 1.4558, "y": 4.109}, {"x": 0.85, "y": 4.109}], "spans": [{"offset": 555, "length": 9}]}, {"content": "27120", "polygon": [{"x": 1.7367, "y": 4.0286}, {"x": 2.0309, "y": 4.0286}, {"x": 2.0309, "y": 4.109}, {"x": 1.7367, "y": 4.109}], "spans": [{"offset": 565, "length": 5}]}, {"content": "623.16", "polygon": [{"x": 3.4147, "y": 4.0272}, {"x": 3.7404, "y": 4.0272}, {"x": 3.7404, "y": 4.1119}, {"x": 3.4147, "y": 4.1119}], "spans": [{"offset": 571, "length": 6}]}, {"content": "No Person Shall Violate,,,,, By Reason Of The", "polygon": [{"x": 5.3955, "y": 4.028}, {"x": 7.6096, "y": 4.028}, {"x": 7.6096, "y": 4.1312}, {"x": 5.3955, "y": 4.1312}], "spans": [{"offset": 578, "length": 45}]}, {"content": "Race", "polygon": [{"x": 5.3958, "y": 4.1545}, {"x": 5.6355, "y": 4.1545}, {"x": 5.6355, "y": 4.2332}, {"x": 5.3958, "y": 4.2332}], "spans": [{"offset": 624, "length": 4}]}, {"content": "Cleveland Division of Police", "polygon": [{"x": 6.3916, "y": 1.696}, {"x": 7.8962, "y": 1.696}, {"x": 7.8962, "y": 1.7921}, {"x": 6.3916, "y": 1.7921}], "spans": [{"offset": 629, "length": 28}]}, {"content": "OHCLP0000", "polygon": [{"x": 6.524, "y": 1.8434}, {"x": 7.2086, "y": 1.8434}, {"x": 7.2086, "y": 1.936}, {"x": 6.524, "y": 1.936}], "spans": [{"offset": 658, "length": 9}]}, {"content": "DOB:", "polygon": [{"x": 6.49, "y": 2.6264}, {"x": 6.7489, "y": 2.6264}, {"x": 6.7489, "y": 2.7071}, {"x": 6.49, "y": 2.7071}], "spans": [{"offset": 668, "length": 4}]}, {"content": "10/27/1961", "polygon": [{"x": 6.984, "y": 2.6252}, {"x": 7.4961, "y": 2.6252}, {"x": 7.4961, "y": 2.71}, {"x": 6.984, "y": 2.71}], "spans": [{"offset": 673, "length": 10}]}, {"content": "Build:", "polygon": [{"x": 6.49, "y": 2.7748}, {"x": 6.7787, "y": 2.7748}, {"x": 6.7787, "y": 2.8541}, {"x": 6.49, "y": 2.8541}], "spans": [{"offset": 684, "length": 6}]}, {"content": "Medium", "polygon": [{"x": 6.9802, "y": 2.7754}, {"x": 7.3528, "y": 2.7754}, {"x": 7.3528, "y": 2.8573}, {"x": 6.9802, "y": 2.8573}], "spans": [{"offset": 691, "length": 6}]}, {"content": "Age:", "polygon": [{"x": 6.482, "y": 2.9218}, {"x": 6.7129, "y": 2.9218}, {"x": 6.7129, "y": 3.0229}, {"x": 6.482, "y": 3.0229}], "spans": [{"offset": 698, "length": 4}]}, {"content": "55", "polygon": [{"x": 6.9767, "y": 2.9235}, {"x": 7.0923, "y": 2.9235}, {"x": 7.0923, "y": 3.0043}, {"x": 6.9767, "y": 3.0043}], "spans": [{"offset": 703, "length": 2}]}, {"content": "State:", "polygon": [{"x": 6.4859, "y": 3.1657}, {"x": 6.7717, "y": 3.1657}, {"x": 6.7717, "y": 3.247}, {"x": 6.4859, "y": 3.247}], "spans": [{"offset": 706, "length": 6}]}, {"content": "Verbal", "polygon": [{"x": 6.6786, "y": 3.3146}, {"x": 6.9853, "y": 3.3146}, {"x": 6.9853, "y": 3.3962}, {"x": 6.6786, "y": 3.3962}], "spans": [{"offset": 713, "length": 6}]}, {"content": "OH", "polygon": [{"x": 6.9774, "y": 3.1662}, {"x": 7.1263, "y": 3.1662}, {"x": 7.1263, "y": 3.2463}, {"x": 6.9774, "y": 3.2463}], "spans": [{"offset": 720, "length": 2}]}, {"content": "Related Weapons", "polygon": [{"x": 0.6077, "y": 4.4218}, {"x": 1.4996, "y": 4.4218}, {"x": 1.4996, "y": 4.5214}, {"x": 0.6077, "y": 4.5214}], "spans": [{"offset": 723, "length": 15}]}, {"content": "Victim/Offender Relationship", "polygon": [{"x": 0.5997, "y": 4.763}, {"x": 2.089, "y": 4.763}, {"x": 2.089, "y": 4.8645}, {"x": 0.5997, "y": 4.8645}], "spans": [{"offset": 739, "length": 28}]}, {"content": "No.", "polygon": [{"x": 0.7069, "y": 4.9623}, {"x": 0.8874, "y": 4.9623}, {"x": 0.8874, "y": 5.0568}, {"x": 0.7069, "y": 5.0568}], "spans": [{"offset": 768, "length": 3}]}, {"content": "Type", "polygon": [{"x": 1.4848, "y": 4.9623}, {"x": 1.7685, "y": 4.9623}, {"x": 1.7685, "y": 5.0786}, {"x": 1.4848, "y": 5.0786}], "spans": [{"offset": 772, "length": 4}]}, {"content": "Name", "polygon": [{"x": 2.7657, "y": 4.9623}, {"x": 3.0882, "y": 4.9623}, {"x": 3.0882, "y": 5.0537}, {"x": 2.7657, "y": 5.0537}], "spans": [{"offset": 777, "length": 4}]}, {"content": "Relationship", "polygon": [{"x": 5.4128, "y": 4.9623}, {"x": 6.1354, "y": 4.9623}, {"x": 6.1354, "y": 5.0769}, {"x": 5.4128, "y": 5.0769}], "spans": [{"offset": 782, "length": 12}]}, {"content": "1", "polygon": [{"x": 0.7095, "y": 5.1379}, {"x": 0.738, "y": 5.1379}, {"x": 0.738, "y": 5.2157}, {"x": 0.7095, "y": 5.2157}], "spans": [{"offset": 795, "length": 1}]}, {"content": "Suspect", "polygon": [{"x": 1.487, "y": 5.1359}, {"x": 1.8712, "y": 5.1359}, {"x": 1.8712, "y": 5.2371}, {"x": 1.487, "y": 5.2371}], "spans": [{"offset": 797, "length": 7}]}, {"content": "Payne,Ronald", "polygon": [{"x": 2.7649, "y": 5.1382}, {"x": 3.433, "y": 5.1382}, {"x": 3.433, "y": 5.239}, {"x": 2.7649, "y": 5.239}], "spans": [{"offset": 805, "length": 12}]}, {"content": "Neighbor", "polygon": [{"x": 5.4119, "y": 5.1382}, {"x": 5.8405, "y": 5.1382}, {"x": 5.8405, "y": 5.2398}, {"x": 5.4119, "y": 5.2398}], "spans": [{"offset": 818, "length": 8}]}, {"content": "Transported By:", "polygon": [{"x": 0.6021, "y": 5.4317}, {"x": 1.4288, "y": 5.4317}, {"x": 1.4288, "y": 5.5327}, {"x": 0.6021, "y": 5.5327}], "spans": [{"offset": 827, "length": 15}]}, {"content": "Extent of Injury:", "polygon": [{"x": 2.9606, "y": 5.4297}, {"x": 3.7721, "y": 5.4297}, {"x": 3.7721, "y": 5.5334}, {"x": 2.9606, "y": 5.5334}], "spans": [{"offset": 843, "length": 17}]}, {"content": "Hospital:", "polygon": [{"x": 5.7057, "y": 5.4317}, {"x": 6.1511, "y": 5.4317}, {"x": 6.1511, "y": 5.5312}, {"x": 5.7057, "y": 5.5312}], "spans": [{"offset": 861, "length": 9}]}, {"content": "Domestic Violence:", "polygon": [{"x": 0.6077, "y": 5.5787}, {"x": 1.5921, "y": 5.5787}, {"x": 1.5921, "y": 5.6608}, {"x": 0.6077, "y": 5.6608}], "spans": [{"offset": 871, "length": 18}]}, {"content": "Condition:", "polygon": [{"x": 0.6048, "y": 5.7245}, {"x": 1.1348, "y": 5.7245}, {"x": 1.1348, "y": 5.8079}, {"x": 0.6048, "y": 5.8079}], "spans": [{"offset": 890, "length": 10}]}, {"content": "Domestic Violence Referrals:", "polygon": [{"x": 2.9606, "y": 5.5767}, {"x": 4.4483, "y": 5.5767}, {"x": 4.4483, "y": 5.6608}, {"x": 2.9606, "y": 5.6608}], "spans": [{"offset": 901, "length": 28}]}, {"content": "Medical Treatment:", "polygon": [{"x": 2.9603, "y": 5.7258}, {"x": 3.9353, "y": 5.7258}, {"x": 3.9353, "y": 5.8058}, {"x": 2.9603, "y": 5.8058}], "spans": [{"offset": 930, "length": 18}]}, {"content": "Federal Agencies Involved:", "polygon": [{"x": 5.7057, "y": 5.5787}, {"x": 7.0987, "y": 5.5787}, {"x": 7.0987, "y": 5.6797}, {"x": 5.7057, "y": 5.6797}], "spans": [{"offset": 949, "length": 26}]}, {"content": "Injury Types", "polygon": [{"x": 0.7063, "y": 5.9231}, {"x": 1.4178, "y": 5.9231}, {"x": 1.4178, "y": 6.0403}, {"x": 0.7063, "y": 6.0403}], "spans": [{"offset": 976, "length": 12}]}, {"content": "Modus Operandi", "polygon": [{"x": 4.5301, "y": 5.9216}, {"x": 5.4791, "y": 5.9216}, {"x": 5.4791, "y": 6.0377}, {"x": 4.5301, "y": 6.0377}], "spans": [{"offset": 989, "length": 14}]}, {"content": "Missing Person Information", "polygon": [{"x": 0.6074, "y": 6.1944}, {"x": 2.0273, "y": 6.1944}, {"x": 2.0273, "y": 6.2974}, {"x": 0.6074, "y": 6.2974}], "spans": [{"offset": 1004, "length": 26}]}, {"content": "Page: 3 of 7", "polygon": [{"x": 0.5819, "y": 10.1525}, {"x": 1.1548, "y": 10.1525}, {"x": 1.1548, "y": 10.2562}, {"x": 0.5819, "y": 10.2562}], "spans": [{"offset": 1031, "length": 12}]}, {"content": "Page: 3 of 6", "polygon": [{"x": 0.608, "y": 10.2036}, {"x": 1.181, "y": 10.2036}, {"x": 1.181, "y": 10.3084}, {"x": 0.608, "y": 10.3084}], "spans": [{"offset": 1044, "length": 12}]}, {"content": "CLEVELAND", "polygon": [{"x": 0.7306, "y": 0.697}, {"x": 1.2177, "y": 0.697}, {"x": 1.2225, "y": 0.8785}, {"x": 0.7258, "y": 0.8737}], "spans": [{"offset": 1057, "length": 9}]}, {"content": "POLICE", "polygon": [{"x": 0.8166, "y": 1.1936}, {"x": 1.1317, "y": 1.2031}, {"x": 1.1317, "y": 1.2938}, {"x": 0.8118, "y": 1.2843}], "spans": [{"offset": 1067, "length": 6}]}, {"content": "You created this PDF from an application that is not licensed to print to novaPDF printer (http://www.novapdf.com)", "polygon": [{"x": 0.3518, "y": 10.7262}, {"x": 7.1038, "y": 10.7262}, {"x": 7.1038, "y": 10.8533}, {"x": 0.3518, "y": 10.8533}], "spans": [{"offset": 1074, "length": 114}]}], "words": [{"content": "Cleveland", "polygon": [{"x": 2.6277, "y": 0.8946}, {"x": 3.7586, "y": 0.8946}, {"x": 3.7586, "y": 1.0779}, {"x": 2.6277, "y": 1.0779}], "span": {"offset": 0, "length": 9}, "confidence": 1.0}, {"content": "Division", "polygon": [{"x": 3.8597, "y": 0.8975}, {"x": 4.7794, "y": 0.8975}, {"x": 4.7794, "y": 1.0842}, {"x": 3.8597, "y": 1.0842}], "span": {"offset": 10, "length": 8}, "confidence": 1.0}, {"content": "of", "polygon": [{"x": 4.874, "y": 0.8931}, {"x": 5.1042, "y": 0.8931}, {"x": 5.1042, "y": 1.0842}, {"x": 4.874, "y": 1.0842}], "span": {"offset": 19, "length": 2}, "confidence": 1.0}, {"content": "Police", "polygon": [{"x": 5.1795, "y": 0.8975}, {"x": 5.8769, "y": 0.8975}, {"x": 5.8769, "y": 1.0842}, {"x": 5.1795, "y": 1.0842}], "span": {"offset": 22, "length": 6}, "confidence": 1.0}, {"content": "Detail", "polygon": [{"x": 3.9535, "y": 1.2567}, {"x": 4.55, "y": 1.2567}, {"x": 4.55, "y": 1.4289}, {"x": 3.9535, "y": 1.4289}], "span": {"offset": 29, "length": 6}, "confidence": 1.0}, {"content": "Print", "polygon": [{"x": 0.6089, "y": 1.6976}, {"x": 0.8762, "y": 1.6976}, {"x": 0.8762, "y": 1.7898}, {"x": 0.6089, "y": 1.7898}], "span": {"offset": 36, "length": 5}, "confidence": 1.0}, {"content": "Date/Time:", "polygon": [{"x": 0.9227, "y": 1.6961}, {"x": 1.5274, "y": 1.6961}, {"x": 1.5274, "y": 1.7898}, {"x": 0.9227, "y": 1.7898}], "span": {"offset": 42, "length": 10}, "confidence": 1.0}, {"content": "Login", "polygon": [{"x": 0.6093, "y": 1.8446}, {"x": 0.9268, "y": 1.8446}, {"x": 0.9268, "y": 1.961}, {"x": 0.6093, "y": 1.961}], "span": {"offset": 53, "length": 5}, "confidence": 1.0}, {"content": "ID:", "polygon": [{"x": 0.9749, "y": 1.8446}, {"x": 1.1194, "y": 1.8446}, {"x": 1.1194, "y": 1.9346}, {"x": 0.9749, "y": 1.9346}], "span": {"offset": 59, "length": 3}, "confidence": 1.0}, {"content": "Case", "polygon": [{"x": 0.6056, "y": 1.9902}, {"x": 0.8912, "y": 1.9902}, {"x": 0.8912, "y": 2.0831}, {"x": 0.6056, "y": 2.0831}], "span": {"offset": 63, "length": 4}, "confidence": 1.0}, {"content": "Number:", "polygon": [{"x": 0.936, "y": 1.9917}, {"x": 1.4226, "y": 1.9917}, {"x": 1.4226, "y": 2.0861}, {"x": 0.936, "y": 2.0861}], "span": {"offset": 68, "length": 7}, "confidence": 1.0}, {"content": "10/12/2018", "polygon": [{"x": 1.6917, "y": 1.6964}, {"x": 2.2893, "y": 1.6964}, {"x": 2.2893, "y": 1.789}, {"x": 1.6917, "y": 1.789}], "span": {"offset": 76, "length": 10}, "confidence": 1.0}, {"content": "10:27", "polygon": [{"x": 2.3394, "y": 1.6964}, {"x": 2.628, "y": 1.6964}, {"x": 2.628, "y": 1.789}, {"x": 2.3394, "y": 1.789}], "span": {"offset": 87, "length": 5}, "confidence": 1.0}, {"content": "mastroip", "polygon": [{"x": 1.6864, "y": 1.8454}, {"x": 2.1478, "y": 1.8454}, {"x": 2.1478, "y": 1.9593}, {"x": 1.6864, "y": 1.9593}], "span": {"offset": 93, "length": 8}, "confidence": 1.0}, {"content": "2017-00253217", "polygon": [{"x": 1.6815, "y": 1.9905}, {"x": 2.5329, "y": 1.9905}, {"x": 2.5329, "y": 2.0866}, {"x": 1.6815, "y": 2.0866}], "span": {"offset": 102, "length": 13}, "confidence": 1.0}, {"content": "ORI", "polygon": [{"x": 5.0398, "y": 1.8432}, {"x": 5.2441, "y": 1.8432}, {"x": 5.2441, "y": 1.936}, {"x": 5.0398, "y": 1.936}], "span": {"offset": 116, "length": 3}, "confidence": 1.0}, {"content": "Number:", "polygon": [{"x": 5.2954, "y": 1.8446}, {"x": 5.7819, "y": 1.8446}, {"x": 5.7819, "y": 1.9391}, {"x": 5.2954, "y": 1.9391}], "span": {"offset": 120, "length": 7}, "confidence": 1.0}, {"content": "Subject", "polygon": [{"x": 0.6041, "y": 2.2843}, {"x": 1.0387, "y": 2.2843}, {"x": 1.0387, "y": 2.403}, {"x": 0.6041, "y": 2.403}], "span": {"offset": 128, "length": 7}, "confidence": 1.0}, {"content": "#", "polygon": [{"x": 1.0782, "y": 2.2843}, {"x": 1.1456, "y": 2.2843}, {"x": 1.1456, "y": 2.3772}, {"x": 1.0782, "y": 2.3772}], "span": {"offset": 136, "length": 1}, "confidence": 1.0}, {"content": "1-Suspect", "polygon": [{"x": 1.4416, "y": 2.2833}, {"x": 1.9483, "y": 2.2833}, {"x": 1.9483, "y": 2.3842}, {"x": 1.4416, "y": 2.3842}], "span": {"offset": 138, "length": 9}, "confidence": 1.0}, {"content": "Primary:", "polygon": [{"x": 0.6077, "y": 2.4807}, {"x": 1.0299, "y": 2.4807}, {"x": 1.0299, "y": 2.5817}, {"x": 0.6077, "y": 2.5817}], "span": {"offset": 148, "length": 8}, "confidence": 1.0}, {"content": "No", "polygon": [{"x": 1.3923, "y": 2.4813}, {"x": 1.5181, "y": 2.4813}, {"x": 1.5181, "y": 2.5627}, {"x": 1.3923, "y": 2.5627}], "span": {"offset": 157, "length": 2}, "confidence": 1.0}, {"content": "Suspect", "polygon": [{"x": 3.5447, "y": 2.4794}, {"x": 3.9647, "y": 2.4794}, {"x": 3.9647, "y": 2.5802}, {"x": 3.5447, "y": 2.5802}], "span": {"offset": 160, "length": 7}, "confidence": 1.0}, {"content": "Type:", "polygon": [{"x": 3.9975, "y": 2.4807}, {"x": 4.2752, "y": 2.4807}, {"x": 4.2752, "y": 2.5817}, {"x": 3.9975, "y": 2.5817}], "span": {"offset": 168, "length": 5}, "confidence": 1.0}, {"content": "Arrested", "polygon": [{"x": 5.0605, "y": 2.4813}, {"x": 5.4622, "y": 2.4813}, {"x": 5.4622, "y": 2.5627}, {"x": 5.0605, "y": 2.5627}], "span": {"offset": 174, "length": 8}, "confidence": 1.0}, {"content": "Name:", "polygon": [{"x": 0.6077, "y": 2.6277}, {"x": 0.922, "y": 2.6277}, {"x": 0.922, "y": 2.7071}, {"x": 0.6077, "y": 2.7071}], "span": {"offset": 183, "length": 5}, "confidence": 1.0}, {"content": "Payne,", "polygon": [{"x": 1.3923, "y": 2.6284}, {"x": 1.7116, "y": 2.6284}, {"x": 1.7116, "y": 2.7292}, {"x": 1.3923, "y": 2.7292}], "span": {"offset": 189, "length": 6}, "confidence": 1.0}, {"content": "Ronald", "polygon": [{"x": 1.7618, "y": 2.6284}, {"x": 2.0897, "y": 2.6284}, {"x": 2.0897, "y": 2.7098}, {"x": 1.7618, "y": 2.7098}], "span": {"offset": 196, "length": 6}, "confidence": 1.0}, {"content": "Race:", "polygon": [{"x": 3.5488, "y": 2.6277}, {"x": 3.8286, "y": 2.6277}, {"x": 3.8286, "y": 2.7071}, {"x": 3.5488, "y": 2.7071}], "span": {"offset": 203, "length": 5}, "confidence": 1.0}, {"content": "White", "polygon": [{"x": 4.0323, "y": 2.6284}, {"x": 4.3056, "y": 2.6284}, {"x": 4.3056, "y": 2.7072}, {"x": 4.0323, "y": 2.7072}], "span": {"offset": 209, "length": 5}, "confidence": 1.0}, {"content": "Sex:", "polygon": [{"x": 4.9173, "y": 2.6264}, {"x": 5.1314, "y": 2.6264}, {"x": 5.1314, "y": 2.7073}, {"x": 4.9173, "y": 2.7073}], "span": {"offset": 215, "length": 4}, "confidence": 1.0}, {"content": "Male", "polygon": [{"x": 5.5097, "y": 2.6284}, {"x": 5.7335, "y": 2.6284}, {"x": 5.7335, "y": 2.7071}, {"x": 5.5097, "y": 2.7071}], "span": {"offset": 220, "length": 4}, "confidence": 1.0}, {"content": "Address:", "polygon": [{"x": 0.5997, "y": 2.7748}, {"x": 1.0593, "y": 2.7748}, {"x": 1.0593, "y": 2.8541}, {"x": 0.5997, "y": 2.8541}], "span": {"offset": 225, "length": 8}, "confidence": 1.0}, {"content": "19310", "polygon": [{"x": 1.3958, "y": 2.7737}, {"x": 1.6816, "y": 2.7737}, {"x": 1.6816, "y": 2.8541}, {"x": 1.3958, "y": 2.8541}], "span": {"offset": 234, "length": 5}, "confidence": 1.0}, {"content": "MUSKOKA", "polygon": [{"x": 1.7252, "y": 2.7731}, {"x": 2.2601, "y": 2.7731}, {"x": 2.2601, "y": 2.8555}, {"x": 1.7252, "y": 2.8555}], "span": {"offset": 240, "length": 7}, "confidence": 1.0}, {"content": "AVE", "polygon": [{"x": 2.2922, "y": 2.7754}, {"x": 2.5022, "y": 2.7754}, {"x": 2.5022, "y": 2.8529}, {"x": 2.2922, "y": 2.8529}], "span": {"offset": 248, "length": 3}, "confidence": 1.0}, {"content": "CLEVELAND", "polygon": [{"x": 1.3877, "y": 2.9211}, {"x": 2.0241, "y": 2.9211}, {"x": 2.0241, "y": 3.0012}, {"x": 1.3877, "y": 3.0012}], "span": {"offset": 252, "length": 9}, "confidence": 1.0}, {"content": "OH", "polygon": [{"x": 2.0656, "y": 2.9211}, {"x": 2.2147, "y": 2.9211}, {"x": 2.2147, "y": 3.0012}, {"x": 2.0656, "y": 3.0012}], "span": {"offset": 262, "length": 2}, "confidence": 1.0}, {"content": "44119", "polygon": [{"x": 2.2576, "y": 2.9222}, {"x": 2.5544, "y": 2.9222}, {"x": 2.5544, "y": 3.0012}, {"x": 2.2576, "y": 3.0012}], "span": {"offset": 265, "length": 5}, "confidence": 1.0}, {"content": "Primary", "polygon": [{"x": 0.6077, "y": 3.1669}, {"x": 1.0028, "y": 3.1669}, {"x": 1.0028, "y": 3.268}, {"x": 0.6077, "y": 3.268}], "span": {"offset": 271, "length": 7}, "confidence": 1.0}, {"content": "Phone:", "polygon": [{"x": 1.0422, "y": 3.1669}, {"x": 1.3928, "y": 3.1669}, {"x": 1.3928, "y": 3.2491}, {"x": 1.0422, "y": 3.2491}], "span": {"offset": 279, "length": 6}, "confidence": 1.0}, {"content": "(216)501-8124", "polygon": [{"x": 1.5866, "y": 3.1644}, {"x": 2.2881, "y": 3.1644}, {"x": 2.2881, "y": 3.2678}, {"x": 1.5866, "y": 3.2678}], "span": {"offset": 286, "length": 13}, "confidence": 1.0}, {"content": "Height:", "polygon": [{"x": 3.5488, "y": 2.7748}, {"x": 3.9062, "y": 2.7748}, {"x": 3.9062, "y": 2.8758}, {"x": 3.5488, "y": 2.8758}], "span": {"offset": 300, "length": 7}, "confidence": 1.0}, {"content": "Eyes:", "polygon": [{"x": 3.5488, "y": 2.9218}, {"x": 3.8215, "y": 2.9218}, {"x": 3.8215, "y": 3.0229}, {"x": 3.5488, "y": 3.0229}], "span": {"offset": 308, "length": 5}, "confidence": 1.0}, {"content": "SSN:", "polygon": [{"x": 3.5447, "y": 3.1657}, {"x": 3.7917, "y": 3.1657}, {"x": 3.7917, "y": 3.2465}, {"x": 3.5447, "y": 3.2465}], "span": {"offset": 314, "length": 4}, "confidence": 1.0}, {"content": "5ft", "polygon": [{"x": 4.0356, "y": 2.7734}, {"x": 4.154, "y": 2.7734}, {"x": 4.154, "y": 2.8572}, {"x": 4.0356, "y": 2.8572}], "span": {"offset": 319, "length": 3}, "confidence": 1.0}, {"content": "11", "polygon": [{"x": 4.1931, "y": 2.7752}, {"x": 4.2821, "y": 2.7752}, {"x": 4.2821, "y": 2.8529}, {"x": 4.1931, "y": 2.8529}], "span": {"offset": 323, "length": 2}, "confidence": 1.0}, {"content": "in", "polygon": [{"x": 4.3421, "y": 2.7754}, {"x": 4.4105, "y": 2.7754}, {"x": 4.4105, "y": 2.8529}, {"x": 4.3421, "y": 2.8529}], "span": {"offset": 326, "length": 2}, "confidence": 1.0}, {"content": "Blue", "polygon": [{"x": 4.039, "y": 2.9225}, {"x": 4.2434, "y": 2.9225}, {"x": 4.2434, "y": 3.0043}, {"x": 4.039, "y": 3.0043}], "span": {"offset": 329, "length": 4}, "confidence": 1.0}, {"content": "Weight:", "polygon": [{"x": 4.9137, "y": 2.7748}, {"x": 5.3, "y": 2.7748}, {"x": 5.3, "y": 2.8758}, {"x": 4.9137, "y": 2.8758}], "span": {"offset": 334, "length": 7}, "confidence": 1.0}, {"content": "Hair:", "polygon": [{"x": 4.9214, "y": 2.9218}, {"x": 5.1508, "y": 2.9218}, {"x": 5.1508, "y": 3.0012}, {"x": 4.9214, "y": 3.0012}], "span": {"offset": 342, "length": 5}, "confidence": 1.0}, {"content": "DVL", "polygon": [{"x": 4.9214, "y": 3.1669}, {"x": 5.1271, "y": 3.1669}, {"x": 5.1271, "y": 3.2451}, {"x": 4.9214, "y": 3.2451}], "span": {"offset": 348, "length": 3}, "confidence": 1.0}, {"content": "#:", "polygon": [{"x": 5.1627, "y": 3.1657}, {"x": 5.2463, "y": 3.1657}, {"x": 5.2463, "y": 3.2463}, {"x": 5.1627, "y": 3.2463}], "span": {"offset": 352, "length": 2}, "confidence": 1.0}, {"content": "250.0", "polygon": [{"x": 5.5046, "y": 2.7737}, {"x": 5.7698, "y": 2.7737}, {"x": 5.7698, "y": 2.8572}, {"x": 5.5046, "y": 2.8572}], "span": {"offset": 355, "length": 5}, "confidence": 1.0}, {"content": "lbs.", "polygon": [{"x": 5.8124, "y": 2.7754}, {"x": 5.9635, "y": 2.7754}, {"x": 5.9635, "y": 2.857}, {"x": 5.8124, "y": 2.857}], "span": {"offset": 361, "length": 4}, "confidence": 1.0}, {"content": "Blonde", "polygon": [{"x": 5.5096, "y": 2.9225}, {"x": 5.8352, "y": 2.9225}, {"x": 5.8352, "y": 3.0039}, {"x": 5.5096, "y": 3.0039}], "span": {"offset": 366, "length": 6}, "confidence": 1.0}, {"content": "or", "polygon": [{"x": 5.8745, "y": 2.9425}, {"x": 5.9704, "y": 2.9425}, {"x": 5.9704, "y": 3.0038}, {"x": 5.8745, "y": 3.0038}], "span": {"offset": 373, "length": 2}, "confidence": 1.0}, {"content": "Strawberry", "polygon": [{"x": 5.5066, "y": 3.0444}, {"x": 6.0219, "y": 3.0444}, {"x": 6.0219, "y": 3.1475}, {"x": 5.5066, "y": 3.1475}], "span": {"offset": 376, "length": 10}, "confidence": 1.0}, {"content": "1", "polygon": [{"x": 5.5395, "y": 3.1915}, {"x": 5.5659, "y": 3.1915}, {"x": 5.5659, "y": 3.2488}, {"x": 5.5395, "y": 3.2488}], "span": {"offset": 387, "length": 1}, "confidence": 1.0}, {"content": "-", "polygon": [{"x": 5.5961, "y": 3.2246}, {"x": 5.6191, "y": 3.2246}, {"x": 5.6191, "y": 3.2316}, {"x": 5.5961, "y": 3.2316}], "span": {"offset": 389, "length": 1}, "confidence": 1.0}, {"content": "MTR", "polygon": [{"x": 5.6442, "y": 3.1918}, {"x": 5.812, "y": 3.1918}, {"x": 5.812, "y": 3.2488}, {"x": 5.6442, "y": 3.2488}], "span": {"offset": 391, "length": 3}, "confidence": 1.0}, {"content": "V...", "polygon": [{"x": 5.8401, "y": 3.1918}, {"x": 5.9399, "y": 3.1918}, {"x": 5.9399, "y": 3.2488}, {"x": 5.8401, "y": 3.2488}], "span": {"offset": 395, "length": 4}, "confidence": 1.0}, {"content": "Resident", "polygon": [{"x": 0.6077, "y": 3.314}, {"x": 1.0595, "y": 3.314}, {"x": 1.0595, "y": 3.394}, {"x": 0.6077, "y": 3.394}], "span": {"offset": 400, "length": 8}, "confidence": 1.0}, {"content": "Type:", "polygon": [{"x": 1.0922, "y": 3.314}, {"x": 1.3699, "y": 3.314}, {"x": 1.3699, "y": 3.415}, {"x": 1.0922, "y": 3.415}], "span": {"offset": 409, "length": 5}, "confidence": 1.0}, {"content": "City", "polygon": [{"x": 1.5838, "y": 3.3133}, {"x": 1.7619, "y": 3.3133}, {"x": 1.7619, "y": 3.4155}, {"x": 1.5838, "y": 3.4155}], "span": {"offset": 415, "length": 4}, "confidence": 1.0}, {"content": "Resident", "polygon": [{"x": 3.0096, "y": 3.314}, {"x": 3.4615, "y": 3.314}, {"x": 3.4615, "y": 3.394}, {"x": 3.0096, "y": 3.394}], "span": {"offset": 420, "length": 8}, "confidence": 1.0}, {"content": "Status:", "polygon": [{"x": 3.4956, "y": 3.3127}, {"x": 3.8503, "y": 3.3127}, {"x": 3.8503, "y": 3.394}, {"x": 3.4956, "y": 3.394}], "span": {"offset": 429, "length": 7}, "confidence": 1.0}, {"content": "Resident", "polygon": [{"x": 4.0396, "y": 3.3146}, {"x": 4.456, "y": 3.3146}, {"x": 4.456, "y": 3.3961}, {"x": 4.0396, "y": 3.3961}], "span": {"offset": 437, "length": 8}, "confidence": 1.0}, {"content": "Statement", "polygon": [{"x": 5.5545, "y": 3.3127}, {"x": 6.0757, "y": 3.3127}, {"x": 6.0757, "y": 3.394}, {"x": 5.5545, "y": 3.394}], "span": {"offset": 446, "length": 9}, "confidence": 1.0}, {"content": "Type:", "polygon": [{"x": 6.1086, "y": 3.314}, {"x": 6.3862, "y": 3.314}, {"x": 6.3862, "y": 3.415}, {"x": 6.1086, "y": 3.415}], "span": {"offset": 456, "length": 5}, "confidence": 1.0}, {"content": "Disposition:", "polygon": [{"x": 0.6077, "y": 3.4611}, {"x": 1.2163, "y": 3.4611}, {"x": 1.2163, "y": 3.5606}, {"x": 0.6077, "y": 3.5606}], "span": {"offset": 462, "length": 12}, "confidence": 1.0}, {"content": "Date:", "polygon": [{"x": 3.5488, "y": 3.4611}, {"x": 3.8013, "y": 3.4611}, {"x": 3.8013, "y": 3.5411}, {"x": 3.5488, "y": 3.5411}], "span": {"offset": 475, "length": 5}, "confidence": 1.0}, {"content": "Custody", "polygon": [{"x": 5.5558, "y": 3.4598}, {"x": 5.9821, "y": 3.4598}, {"x": 5.9821, "y": 3.5621}, {"x": 5.5558, "y": 3.5621}], "span": {"offset": 481, "length": 7}, "confidence": 1.0}, {"content": "Status:", "polygon": [{"x": 6.0219, "y": 3.4598}, {"x": 6.3734, "y": 3.4598}, {"x": 6.3734, "y": 3.5411}, {"x": 6.0219, "y": 3.5411}], "span": {"offset": 489, "length": 7}, "confidence": 1.0}, {"content": "Related", "polygon": [{"x": 0.6077, "y": 3.6571}, {"x": 0.986, "y": 3.6571}, {"x": 0.986, "y": 3.7372}, {"x": 0.6077, "y": 3.7372}], "span": {"offset": 497, "length": 7}, "confidence": 1.0}, {"content": "Offenses", "polygon": [{"x": 1.0292, "y": 3.6552}, {"x": 1.4842, "y": 3.6552}, {"x": 1.4842, "y": 3.7365}, {"x": 1.0292, "y": 3.7365}], "span": {"offset": 505, "length": 8}, "confidence": 1.0}, {"content": "Group/ORI", "polygon": [{"x": 0.7012, "y": 3.8519}, {"x": 1.2418, "y": 3.8519}, {"x": 1.2418, "y": 3.9528}, {"x": 0.7012, "y": 3.9528}], "span": {"offset": 514, "length": 9}, "confidence": 1.0}, {"content": "Crime", "polygon": [{"x": 1.7388, "y": 3.8519}, {"x": 2.0385, "y": 3.8519}, {"x": 2.0385, "y": 3.9326}, {"x": 1.7388, "y": 3.9326}], "span": {"offset": 524, "length": 5}, "confidence": 1.0}, {"content": "Code", "polygon": [{"x": 2.0786, "y": 3.8519}, {"x": 2.3421, "y": 3.8519}, {"x": 2.3421, "y": 3.9353}, {"x": 2.0786, "y": 3.9353}], "span": {"offset": 530, "length": 4}, "confidence": 1.0}, {"content": "Statute", "polygon": [{"x": 3.4173, "y": 3.8519}, {"x": 3.7782, "y": 3.8519}, {"x": 3.7782, "y": 3.9333}, {"x": 3.4173, "y": 3.9333}], "span": {"offset": 535, "length": 7}, "confidence": 1.0}, {"content": "Description", "polygon": [{"x": 5.3952, "y": 3.8532}, {"x": 5.9784, "y": 3.8532}, {"x": 5.9784, "y": 3.9528}, {"x": 5.3952, "y": 3.9528}], "span": {"offset": 543, "length": 11}, "confidence": 1.0}, {"content": "OHCLP0000", "polygon": [{"x": 0.85, "y": 4.0286}, {"x": 1.4558, "y": 4.0286}, {"x": 1.4558, "y": 4.109}, {"x": 0.85, "y": 4.109}], "span": {"offset": 555, "length": 9}, "confidence": 1.0}, {"content": "27120", "polygon": [{"x": 1.7367, "y": 4.0286}, {"x": 2.0309, "y": 4.0286}, {"x": 2.0309, "y": 4.109}, {"x": 1.7367, "y": 4.109}], "span": {"offset": 565, "length": 5}, "confidence": 1.0}, {"content": "623.16", "polygon": [{"x": 3.4147, "y": 4.0272}, {"x": 3.7404, "y": 4.0272}, {"x": 3.7404, "y": 4.1119}, {"x": 3.4147, "y": 4.1119}], "span": {"offset": 571, "length": 6}, "confidence": 1.0}, {"content": "No", "polygon": [{"x": 5.3955, "y": 4.0303}, {"x": 5.5219, "y": 4.0303}, {"x": 5.5219, "y": 4.1117}, {"x": 5.3955, "y": 4.1117}], "span": {"offset": 578, "length": 2}, "confidence": 1.0}, {"content": "Person", "polygon": [{"x": 5.5655, "y": 4.0303}, {"x": 5.8937, "y": 4.0303}, {"x": 5.8937, "y": 4.1117}, {"x": 5.5655, "y": 4.1117}], "span": {"offset": 581, "length": 6}, "confidence": 1.0}, {"content": "Shall", "polygon": [{"x": 5.9378, "y": 4.028}, {"x": 6.1651, "y": 4.028}, {"x": 6.1651, "y": 4.109}, {"x": 5.9378, "y": 4.109}], "span": {"offset": 588, "length": 5}, "confidence": 1.0}, {"content": "Violate,,,,,", "polygon": [{"x": 6.2047, "y": 4.0303}, {"x": 6.6787, "y": 4.0303}, {"x": 6.6787, "y": 4.1231}, {"x": 6.2047, "y": 4.1231}], "span": {"offset": 594, "length": 12}, "confidence": 1.0}, {"content": "By", "polygon": [{"x": 6.7286, "y": 4.0303}, {"x": 6.8432, "y": 4.0303}, {"x": 6.8432, "y": 4.1312}, {"x": 6.7286, "y": 4.1312}], "span": {"offset": 607, "length": 2}, "confidence": 1.0}, {"content": "Reason", "polygon": [{"x": 6.8861, "y": 4.0303}, {"x": 7.2439, "y": 4.0303}, {"x": 7.2439, "y": 4.1117}, {"x": 6.8861, "y": 4.1117}], "span": {"offset": 610, "length": 6}, "confidence": 1.0}, {"content": "Of", "polygon": [{"x": 7.2879, "y": 4.0283}, {"x": 7.4014, "y": 4.0283}, {"x": 7.4014, "y": 4.109}, {"x": 7.2879, "y": 4.109}], "span": {"offset": 617, "length": 2}, "confidence": 1.0}, {"content": "The", "polygon": [{"x": 7.429, "y": 4.0303}, {"x": 7.6096, "y": 4.0303}, {"x": 7.6096, "y": 4.109}, {"x": 7.429, "y": 4.109}], "span": {"offset": 620, "length": 3}, "confidence": 1.0}, {"content": "Race", "polygon": [{"x": 5.3958, "y": 4.1545}, {"x": 5.6355, "y": 4.1545}, {"x": 5.6355, "y": 4.2332}, {"x": 5.3958, "y": 4.2332}], "span": {"offset": 624, "length": 4}, "confidence": 1.0}, {"content": "Cleveland", "polygon": [{"x": 6.3916, "y": 1.6967}, {"x": 6.9242, "y": 1.6967}, {"x": 6.9242, "y": 1.7921}, {"x": 6.3916, "y": 1.7921}], "span": {"offset": 629, "length": 9}, "confidence": 1.0}, {"content": "Division", "polygon": [{"x": 6.9758, "y": 1.6983}, {"x": 7.3871, "y": 1.6983}, {"x": 7.3871, "y": 1.792}, {"x": 6.9758, "y": 1.792}], "span": {"offset": 639, "length": 8}, "confidence": 1.0}, {"content": "of", "polygon": [{"x": 7.4343, "y": 1.696}, {"x": 7.5378, "y": 1.696}, {"x": 7.5378, "y": 1.792}, {"x": 7.4343, "y": 1.792}], "span": {"offset": 648, "length": 2}, "confidence": 1.0}, {"content": "Police", "polygon": [{"x": 7.5771, "y": 1.6983}, {"x": 7.8962, "y": 1.6983}, {"x": 7.8962, "y": 1.792}, {"x": 7.5771, "y": 1.792}], "span": {"offset": 651, "length": 6}, "confidence": 1.0}, {"content": "OHCLP0000", "polygon": [{"x": 6.524, "y": 1.8434}, {"x": 7.2086, "y": 1.8434}, {"x": 7.2086, "y": 1.936}, {"x": 6.524, "y": 1.936}], "span": {"offset": 658, "length": 9}, "confidence": 1.0}, {"content": "DOB:", "polygon": [{"x": 6.49, "y": 2.6264}, {"x": 6.7489, "y": 2.6264}, {"x": 6.7489, "y": 2.7071}, {"x": 6.49, "y": 2.7071}], "span": {"offset": 668, "length": 4}, "confidence": 1.0}, {"content": "10/27/1961", "polygon": [{"x": 6.984, "y": 2.6252}, {"x": 7.4961, "y": 2.6252}, {"x": 7.4961, "y": 2.71}, {"x": 6.984, "y": 2.71}], "span": {"offset": 673, "length": 10}, "confidence": 1.0}, {"content": "Build:", "polygon": [{"x": 6.49, "y": 2.7748}, {"x": 6.7787, "y": 2.7748}, {"x": 6.7787, "y": 2.8541}, {"x": 6.49, "y": 2.8541}], "span": {"offset": 684, "length": 6}, "confidence": 1.0}, {"content": "Medium", "polygon": [{"x": 6.9802, "y": 2.7754}, {"x": 7.3528, "y": 2.7754}, {"x": 7.3528, "y": 2.8573}, {"x": 6.9802, "y": 2.8573}], "span": {"offset": 691, "length": 6}, "confidence": 1.0}, {"content": "Age:", "polygon": [{"x": 6.482, "y": 2.9218}, {"x": 6.7129, "y": 2.9218}, {"x": 6.7129, "y": 3.0229}, {"x": 6.482, "y": 3.0229}], "span": {"offset": 698, "length": 4}, "confidence": 1.0}, {"content": "55", "polygon": [{"x": 6.9767, "y": 2.9235}, {"x": 7.0923, "y": 2.9235}, {"x": 7.0923, "y": 3.0043}, {"x": 6.9767, "y": 3.0043}], "span": {"offset": 703, "length": 2}, "confidence": 1.0}, {"content": "State:", "polygon": [{"x": 6.4859, "y": 3.1657}, {"x": 6.7717, "y": 3.1657}, {"x": 6.7717, "y": 3.247}, {"x": 6.4859, "y": 3.247}], "span": {"offset": 706, "length": 6}, "confidence": 1.0}, {"content": "Verbal", "polygon": [{"x": 6.6786, "y": 3.3146}, {"x": 6.9853, "y": 3.3146}, {"x": 6.9853, "y": 3.3962}, {"x": 6.6786, "y": 3.3962}], "span": {"offset": 713, "length": 6}, "confidence": 1.0}, {"content": "OH", "polygon": [{"x": 6.9774, "y": 3.1662}, {"x": 7.1263, "y": 3.1662}, {"x": 7.1263, "y": 3.2463}, {"x": 6.9774, "y": 3.2463}], "span": {"offset": 720, "length": 2}, "confidence": 1.0}, {"content": "Related", "polygon": [{"x": 0.6077, "y": 4.4218}, {"x": 0.986, "y": 4.4218}, {"x": 0.986, "y": 4.5019}, {"x": 0.6077, "y": 4.5019}], "span": {"offset": 723, "length": 7}, "confidence": 1.0}, {"content": "Weapons", "polygon": [{"x": 1.0248, "y": 4.4218}, {"x": 1.4996, "y": 4.4218}, {"x": 1.4996, "y": 4.5214}, {"x": 1.0248, "y": 4.5214}], "span": {"offset": 731, "length": 7}, "confidence": 1.0}, {"content": "Victim/Offender", "polygon": [{"x": 0.5997, "y": 4.763}, {"x": 1.4112, "y": 4.763}, {"x": 1.4112, "y": 4.845}, {"x": 0.5997, "y": 4.845}], "span": {"offset": 739, "length": 15}, "confidence": 1.0}, {"content": "Relationship", "polygon": [{"x": 1.4473, "y": 4.765}, {"x": 2.089, "y": 4.765}, {"x": 2.089, "y": 4.8645}, {"x": 1.4473, "y": 4.8645}], "span": {"offset": 755, "length": 12}, "confidence": 1.0}, {"content": "No.", "polygon": [{"x": 0.7069, "y": 4.9623}, {"x": 0.8874, "y": 4.9623}, {"x": 0.8874, "y": 5.0568}, {"x": 0.7069, "y": 5.0568}], "span": {"offset": 768, "length": 3}, "confidence": 1.0}, {"content": "Type", "polygon": [{"x": 1.4848, "y": 4.9623}, {"x": 1.7685, "y": 4.9623}, {"x": 1.7685, "y": 5.0786}, {"x": 1.4848, "y": 5.0786}], "span": {"offset": 772, "length": 4}, "confidence": 1.0}, {"content": "Name", "polygon": [{"x": 2.7657, "y": 4.9623}, {"x": 3.0882, "y": 4.9623}, {"x": 3.0882, "y": 5.0537}, {"x": 2.7657, "y": 5.0537}], "span": {"offset": 777, "length": 4}, "confidence": 1.0}, {"content": "Relationship", "polygon": [{"x": 5.4128, "y": 4.9623}, {"x": 6.1354, "y": 4.9623}, {"x": 6.1354, "y": 5.0769}, {"x": 5.4128, "y": 5.0769}], "span": {"offset": 782, "length": 12}, "confidence": 1.0}, {"content": "1", "polygon": [{"x": 0.7095, "y": 5.1379}, {"x": 0.738, "y": 5.1379}, {"x": 0.738, "y": 5.2157}, {"x": 0.7095, "y": 5.2157}], "span": {"offset": 795, "length": 1}, "confidence": 1.0}, {"content": "Suspect", "polygon": [{"x": 1.487, "y": 5.1359}, {"x": 1.8712, "y": 5.1359}, {"x": 1.8712, "y": 5.2371}, {"x": 1.487, "y": 5.2371}], "span": {"offset": 797, "length": 7}, "confidence": 1.0}, {"content": "Payne,Ronald", "polygon": [{"x": 2.7649, "y": 5.1382}, {"x": 3.433, "y": 5.1382}, {"x": 3.433, "y": 5.239}, {"x": 2.7649, "y": 5.239}], "span": {"offset": 805, "length": 12}, "confidence": 1.0}, {"content": "Neighbor", "polygon": [{"x": 5.4119, "y": 5.1382}, {"x": 5.8405, "y": 5.1382}, {"x": 5.8405, "y": 5.2398}, {"x": 5.4119, "y": 5.2398}], "span": {"offset": 818, "length": 8}, "confidence": 1.0}, {"content": "Transported", "polygon": [{"x": 0.6021, "y": 5.4317}, {"x": 1.2285, "y": 5.4317}, {"x": 1.2285, "y": 5.5312}, {"x": 0.6021, "y": 5.5312}], "span": {"offset": 827, "length": 11}, "confidence": 1.0}, {"content": "By:", "polygon": [{"x": 1.2745, "y": 5.4317}, {"x": 1.4288, "y": 5.4317}, {"x": 1.4288, "y": 5.5327}, {"x": 1.2745, "y": 5.5327}], "span": {"offset": 839, "length": 3}, "confidence": 1.0}, {"content": "Extent", "polygon": [{"x": 2.9606, "y": 5.4317}, {"x": 3.2848, "y": 5.4317}, {"x": 3.2848, "y": 5.5117}, {"x": 2.9606, "y": 5.5117}], "span": {"offset": 843, "length": 6}, "confidence": 1.0}, {"content": "of", "polygon": [{"x": 3.3197, "y": 5.4297}, {"x": 3.4203, "y": 5.4297}, {"x": 3.4203, "y": 5.5138}, {"x": 3.3197, "y": 5.5138}], "span": {"offset": 850, "length": 2}, "confidence": 1.0}, {"content": "Injury:", "polygon": [{"x": 3.4568, "y": 5.4317}, {"x": 3.7721, "y": 5.4317}, {"x": 3.7721, "y": 5.5334}, {"x": 3.4568, "y": 5.5334}], "span": {"offset": 853, "length": 7}, "confidence": 1.0}, {"content": "Hospital:", "polygon": [{"x": 5.7057, "y": 5.4317}, {"x": 6.1511, "y": 5.4317}, {"x": 6.1511, "y": 5.5312}, {"x": 5.7057, "y": 5.5312}], "span": {"offset": 861, "length": 9}, "confidence": 1.0}, {"content": "Domestic", "polygon": [{"x": 0.6077, "y": 5.5787}, {"x": 1.0858, "y": 5.5787}, {"x": 1.0858, "y": 5.6608}, {"x": 0.6077, "y": 5.6608}], "span": {"offset": 871, "length": 8}, "confidence": 1.0}, {"content": "Violence:", "polygon": [{"x": 1.1193, "y": 5.5787}, {"x": 1.5921, "y": 5.5787}, {"x": 1.5921, "y": 5.6608}, {"x": 1.1193, "y": 5.6608}], "span": {"offset": 880, "length": 9}, "confidence": 1.0}, {"content": "Condition:", "polygon": [{"x": 0.6048, "y": 5.7245}, {"x": 1.1348, "y": 5.7245}, {"x": 1.1348, "y": 5.8079}, {"x": 0.6048, "y": 5.8079}], "span": {"offset": 890, "length": 10}, "confidence": 1.0}, {"content": "Domestic", "polygon": [{"x": 2.9606, "y": 5.5787}, {"x": 3.4387, "y": 5.5787}, {"x": 3.4387, "y": 5.6608}, {"x": 2.9606, "y": 5.6608}], "span": {"offset": 901, "length": 8}, "confidence": 1.0}, {"content": "Violence", "polygon": [{"x": 3.4722, "y": 5.5787}, {"x": 3.9169, "y": 5.5787}, {"x": 3.9169, "y": 5.6608}, {"x": 3.4722, "y": 5.6608}], "span": {"offset": 910, "length": 8}, "confidence": 1.0}, {"content": "Referrals:", "polygon": [{"x": 3.9606, "y": 5.5767}, {"x": 4.4483, "y": 5.5767}, {"x": 4.4483, "y": 5.6581}, {"x": 3.9606, "y": 5.6581}], "span": {"offset": 919, "length": 10}, "confidence": 1.0}, {"content": "Medical", "polygon": [{"x": 2.9603, "y": 5.7258}, {"x": 3.3444, "y": 5.7258}, {"x": 3.3444, "y": 5.8051}, {"x": 2.9603, "y": 5.8051}], "span": {"offset": 930, "length": 7}, "confidence": 1.0}, {"content": "Treatment:", "polygon": [{"x": 3.3864, "y": 5.7258}, {"x": 3.9353, "y": 5.7258}, {"x": 3.9353, "y": 5.8058}, {"x": 3.3864, "y": 5.8058}], "span": {"offset": 938, "length": 10}, "confidence": 1.0}, {"content": "Federal", "polygon": [{"x": 5.7057, "y": 5.5787}, {"x": 6.0768, "y": 5.5787}, {"x": 6.0768, "y": 5.6581}, {"x": 5.7057, "y": 5.6581}], "span": {"offset": 949, "length": 7}, "confidence": 1.0}, {"content": "Agencies", "polygon": [{"x": 6.116, "y": 5.5787}, {"x": 6.593, "y": 5.5787}, {"x": 6.593, "y": 5.6797}, {"x": 6.116, "y": 5.6797}], "span": {"offset": 957, "length": 8}, "confidence": 1.0}, {"content": "Involved:", "polygon": [{"x": 6.6366, "y": 5.5787}, {"x": 7.0987, "y": 5.5787}, {"x": 7.0987, "y": 5.6608}, {"x": 6.6366, "y": 5.6608}], "span": {"offset": 966, "length": 9}, "confidence": 1.0}, {"content": "Injury", "polygon": [{"x": 0.7063, "y": 5.9231}, {"x": 1.0295, "y": 5.9231}, {"x": 1.0295, "y": 6.0403}, {"x": 0.7063, "y": 6.0403}], "span": {"offset": 976, "length": 6}, "confidence": 1.0}, {"content": "Types", "polygon": [{"x": 1.07, "y": 5.9231}, {"x": 1.4178, "y": 5.9231}, {"x": 1.4178, "y": 6.0394}, {"x": 1.07, "y": 6.0394}], "span": {"offset": 983, "length": 5}, "confidence": 1.0}, {"content": "Modus", "polygon": [{"x": 4.5301, "y": 5.9231}, {"x": 4.9128, "y": 5.9231}, {"x": 4.9128, "y": 6.0176}, {"x": 4.5301, "y": 6.0176}], "span": {"offset": 989, "length": 5}, "confidence": 1.0}, {"content": "Operandi", "polygon": [{"x": 4.9552, "y": 5.9216}, {"x": 5.4791, "y": 5.9216}, {"x": 5.4791, "y": 6.0377}, {"x": 4.9552, "y": 6.0377}], "span": {"offset": 995, "length": 8}, "confidence": 1.0}, {"content": "Missing", "polygon": [{"x": 0.6074, "y": 6.1964}, {"x": 0.9981, "y": 6.1964}, {"x": 0.9981, "y": 6.2974}, {"x": 0.6074, "y": 6.2974}], "span": {"offset": 1004, "length": 7}, "confidence": 1.0}, {"content": "Person", "polygon": [{"x": 1.0424, "y": 6.1964}, {"x": 1.3972, "y": 6.1964}, {"x": 1.3972, "y": 6.2785}, {"x": 1.0424, "y": 6.2785}], "span": {"offset": 1012, "length": 6}, "confidence": 1.0}, {"content": "Information", "polygon": [{"x": 1.4438, "y": 6.1944}, {"x": 2.0273, "y": 6.1944}, {"x": 2.0273, "y": 6.2785}, {"x": 1.4438, "y": 6.2785}], "span": {"offset": 1019, "length": 11}, "confidence": 1.0}, {"content": "Page:", "polygon": [{"x": 0.5819, "y": 10.1545}, {"x": 0.8481, "y": 10.1545}, {"x": 0.8481, "y": 10.2562}, {"x": 0.5819, "y": 10.2562}], "span": {"offset": 1031, "length": 5}, "confidence": 1.0}, {"content": "3", "polygon": [{"x": 0.8918, "y": 10.1543}, {"x": 0.9425, "y": 10.1543}, {"x": 0.9425, "y": 10.2332}, {"x": 0.8918, "y": 10.2332}], "span": {"offset": 1037, "length": 1}, "confidence": 1.0}, {"content": "of", "polygon": [{"x": 0.9823, "y": 10.1525}, {"x": 1.0746, "y": 10.1525}, {"x": 1.0746, "y": 10.2359}, {"x": 0.9823, "y": 10.2359}], "span": {"offset": 1039, "length": 2}, "confidence": 1.0}, {"content": "7", "polygon": [{"x": 1.1047, "y": 10.1555}, {"x": 1.1548, "y": 10.1555}, {"x": 1.1548, "y": 10.232}, {"x": 1.1047, "y": 10.232}], "span": {"offset": 1042, "length": 1}, "confidence": 1.0}, {"content": "Page:", "polygon": [{"x": 0.608, "y": 10.2068}, {"x": 0.8742, "y": 10.2068}, {"x": 0.8742, "y": 10.3084}, {"x": 0.608, "y": 10.3084}], "span": {"offset": 1044, "length": 5}, "confidence": 1.0}, {"content": "3", "polygon": [{"x": 0.9179, "y": 10.2065}, {"x": 0.9687, "y": 10.2065}, {"x": 0.9687, "y": 10.2855}, {"x": 0.9179, "y": 10.2855}], "span": {"offset": 1050, "length": 1}, "confidence": 1.0}, {"content": "of", "polygon": [{"x": 1.0084, "y": 10.2047}, {"x": 1.1007, "y": 10.2047}, {"x": 1.1007, "y": 10.2881}, {"x": 1.0084, "y": 10.2881}], "span": {"offset": 1052, "length": 2}, "confidence": 1.0}, {"content": "6", "polygon": [{"x": 1.127, "y": 10.2036}, {"x": 1.181, "y": 10.2036}, {"x": 1.181, "y": 10.2884}, {"x": 1.127, "y": 10.2884}], "span": {"offset": 1055, "length": 1}, "confidence": 1.0}, {"content": "CLEVELAND", "polygon": [{"x": 0.7349, "y": 0.697}, {"x": 1.2218, "y": 0.697}, {"x": 1.221, "y": 0.8784}, {"x": 0.734, "y": 0.8761}], "span": {"offset": 1057, "length": 9}, "confidence": 0.65}, {"content": "POLICE", "polygon": [{"x": 0.8219, "y": 1.1973}, {"x": 1.1221, "y": 1.2073}, {"x": 1.125, "y": 1.2938}, {"x": 0.8157, "y": 1.2863}], "span": {"offset": 1067, "length": 6}, "confidence": 0.993}, {"content": "You", "polygon": [{"x": 0.3518, "y": 10.7288}, {"x": 0.5807, "y": 10.7288}, {"x": 0.5807, "y": 10.8305}, {"x": 0.3518, "y": 10.8305}], "span": {"offset": 1074, "length": 3}, "confidence": 1.0}, {"content": "created", "polygon": [{"x": 0.6326, "y": 10.7288}, {"x": 1.0649, "y": 10.7288}, {"x": 1.0649, "y": 10.83}, {"x": 0.6326, "y": 10.83}], "span": {"offset": 1078, "length": 7}, "confidence": 1.0}, {"content": "this", "polygon": [{"x": 1.1137, "y": 10.7288}, {"x": 1.315, "y": 10.7288}, {"x": 1.315, "y": 10.8284}, {"x": 1.1137, "y": 10.8284}], "span": {"offset": 1086, "length": 4}, "confidence": 1.0}, {"content": "PDF", "polygon": [{"x": 1.3677, "y": 10.7288}, {"x": 1.6196, "y": 10.7288}, {"x": 1.6196, "y": 10.8251}, {"x": 1.3677, "y": 10.8251}], "span": {"offset": 1091, "length": 3}, "confidence": 1.0}, {"content": "from", "polygon": [{"x": 1.6638, "y": 10.7262}, {"x": 1.9226, "y": 10.7262}, {"x": 1.9226, "y": 10.8299}, {"x": 1.6638, "y": 10.8299}], "span": {"offset": 1095, "length": 4}, "confidence": 1.0}, {"content": "an", "polygon": [{"x": 1.9728, "y": 10.7498}, {"x": 2.1081, "y": 10.7498}, {"x": 2.1081, "y": 10.8266}, {"x": 1.9728, "y": 10.8266}], "span": {"offset": 1100, "length": 2}, "confidence": 1.0}, {"content": "application", "polygon": [{"x": 2.1592, "y": 10.7288}, {"x": 2.786, "y": 10.7288}, {"x": 2.786, "y": 10.8517}, {"x": 2.1592, "y": 10.8517}], "span": {"offset": 1103, "length": 11}, "confidence": 1.0}, {"content": "that", "polygon": [{"x": 2.8345, "y": 10.7288}, {"x": 3.055, "y": 10.7288}, {"x": 3.055, "y": 10.8267}, {"x": 2.8345, "y": 10.8267}], "span": {"offset": 1115, "length": 4}, "confidence": 1.0}, {"content": "is", "polygon": [{"x": 3.102, "y": 10.7288}, {"x": 3.1849, "y": 10.7288}, {"x": 3.1849, "y": 10.8284}, {"x": 3.102, "y": 10.8284}], "span": {"offset": 1120, "length": 2}, "confidence": 1.0}, {"content": "not", "polygon": [{"x": 3.2361, "y": 10.7309}, {"x": 3.4125, "y": 10.7309}, {"x": 3.4125, "y": 10.8299}, {"x": 3.2361, "y": 10.8299}], "span": {"offset": 1123, "length": 3}, "confidence": 1.0}, {"content": "licensed", "polygon": [{"x": 3.4593, "y": 10.7288}, {"x": 3.9329, "y": 10.7288}, {"x": 3.9329, "y": 10.83}, {"x": 3.4593, "y": 10.83}], "span": {"offset": 1127, "length": 8}, "confidence": 1.0}, {"content": "to", "polygon": [{"x": 3.9821, "y": 10.7309}, {"x": 4.0868, "y": 10.7309}, {"x": 4.0868, "y": 10.8299}, {"x": 3.9821, "y": 10.8299}], "span": {"offset": 1136, "length": 2}, "confidence": 1.0}, {"content": "print", "polygon": [{"x": 4.1377, "y": 10.7288}, {"x": 4.3886, "y": 10.7288}, {"x": 4.3886, "y": 10.8517}, {"x": 4.1377, "y": 10.8517}], "span": {"offset": 1139, "length": 5}, "confidence": 1.0}, {"content": "to", "polygon": [{"x": 4.4289, "y": 10.7309}, {"x": 4.5337, "y": 10.7309}, {"x": 4.5337, "y": 10.8299}, {"x": 4.4289, "y": 10.8299}], "span": {"offset": 1145, "length": 2}, "confidence": 1.0}, {"content": "novaPDF", "polygon": [{"x": 4.5847, "y": 10.7288}, {"x": 5.1285, "y": 10.7288}, {"x": 5.1285, "y": 10.8299}, {"x": 4.5847, "y": 10.8299}], "span": {"offset": 1148, "length": 7}, "confidence": 1.0}, {"content": "printer", "polygon": [{"x": 5.1806, "y": 10.7288}, {"x": 5.5536, "y": 10.7288}, {"x": 5.5536, "y": 10.8517}, {"x": 5.1806, "y": 10.8517}], "span": {"offset": 1156, "length": 7}, "confidence": 1.0}, {"content": "(http://www.novapdf.com)", "polygon": [{"x": 5.597, "y": 10.7262}, {"x": 7.1038, "y": 10.7262}, {"x": 7.1038, "y": 10.8533}, {"x": 5.597, "y": 10.8533}], "span": {"offset": 1164, "length": 24}, "confidence": 1.0}], "selection_marks": [], "spans": [{"offset": 0, "length": 1188}]}], "paragraphs": [], "tables": [{"row_count": 10, "column_count": 6, "cells": [{"kind": "columnHeader", "row_index": 0, "column_index": 0, "row_span": 1, "column_span": 1, "content": "Print Date/Time: Login ID: Case Number:", "bounding_regions": [{"page_number": 3, "polygon": [{"x": 0.532, "y": 1.6227}, {"x": 1.574, "y": 1.6153}, {"x": 1.5665, "y": 2.1865}, {"x": 0.5394, "y": 2.1865}]}], "spans": [{"offset": 36, "length": 39}]}, {"kind": "columnHeader", "row_index": 0, "column_index": 1, "row_span": 1, "column_span": 1, "content": "10/12/2018 10:27 mastroip 2017-00253217", "bounding_regions": [{"page_number": 3, "polygon": [{"x": 1.574, "y": 1.6153}, {"x": 2.7946, "y": 1.608}, {"x": 2.802, "y": 2.1865}, {"x": 1.5665, "y": 2.1865}]}], "spans": [{"offset": 76, "length": 39}]}, {"kind": "columnHeader", "row_index": 0, "column_index": 2, "row_span": 1, "column_span": 1, "content": "", "bounding_regions": [{"page_number": 3, "polygon": [{"x": 2.7946, "y": 1.608}, {"x": 3.9556, "y": 1.6153}, {"x": 3.9631, "y": 2.1791}, {"x": 2.802, "y": 2.1865}]}], "spans": []}, {"kind": "columnHeader", "row_index": 0, "column_index": 3, "row_span": 1, "column_span": 1, "content": "", "bounding_regions": [{"page_number": 3, "polygon": [{"x": 3.9556, "y": 1.6153}, {"x": 4.685, "y": 1.6153}, {"x": 4.685, "y": 2.1791}, {"x": 3.9631, "y": 2.1791}]}], "spans": []}, {"kind": "columnHeader", "row_index": 0, "column_index": 4, "row_span": 1, "column_span": 2, "content": "ORI Number:", "bounding_regions": [{"page_number": 3, "polygon": [{"x": 4.685, "y": 1.6153}, {"x": 6.3596, "y": 1.6227}, {"x": 6.3671, "y": 2.1791}, {"x": 4.685, "y": 2.1791}]}], "spans": [{"offset": 116, "length": 11}]}, {"kind": "content", "row_index": 1, "column_index": 0, "row_span": 1, "column_span": 2, "content": "Subject # 1-Suspect", "bounding_regions": [{"page_number": 3, "polygon": [{"x": 0.5394, "y": 2.1865}, {"x": 2.802, "y": 2.1865}, {"x": 2.802, "y": 2.4208}, {"x": 0.5394, "y": 2.4208}]}], "spans": [{"offset": 128, "length": 19}]}, {"kind": "content", "row_index": 1, "column_index": 2, "row_span": 1, "column_span": 2, "content": "", "bounding_regions": [{"page_number": 3, "polygon": [{"x": 2.802, "y": 2.1865}, {"x": 4.685, "y": 2.1791}, {"x": 4.685, "y": 2.4208}, {"x": 2.802, "y": 2.4208}]}], "spans": []}, {"kind": "content", "row_index": 1, "column_index": 4, "row_span": 1, "column_span": 2, "content": "", "bounding_regions": [{"page_number": 3, "polygon": [{"x": 4.685, "y": 2.1791}, {"x": 6.3671, "y": 2.1791}, {"x": 6.3745, "y": 2.4281}, {"x": 4.685, "y": 2.4208}]}], "spans": []}, {"kind": "content", "row_index": 2, "column_index": 0, "row_span": 1, "column_span": 2, "content": "Primary: No", "bounding_regions": [{"page_number": 3, "polygon": [{"x": 0.5394, "y": 2.4208}, {"x": 2.802, "y": 2.4208}, {"x": 2.802, "y": 2.5965}, {"x": 0.5394, "y": 2.5965}]}], "spans": [{"offset": 148, "length": 11}]}, {"kind": "content", "row_index": 2, "column_index": 2, "row_span": 1, "column_span": 2, "content": "Suspect Type:", "bounding_regions": [{"page_number": 3, "polygon": [{"x": 2.802, "y": 2.4208}, {"x": 4.685, "y": 2.4208}, {"x": 4.685, "y": 2.5965}, {"x": 2.802, "y": 2.5965}]}], "spans": [{"offset": 160, "length": 13}]}, {"kind": "content", "row_index": 2, "column_index": 4, "row_span": 1, "column_span": 2, "content": "Arrested", "bounding_regions": [{"page_number": 3, "polygon": [{"x": 4.685, "y": 2.4208}, {"x": 6.3745, "y": 2.4281}, {"x": 6.3745, "y": 2.5892}, {"x": 4.685, "y": 2.5965}]}], "spans": [{"offset": 174, "length": 8}]}, {"kind": "content", "row_index": 3, "column_index": 0, "row_span": 1, "column_span": 1, "content": "Name: Payne,", "bounding_regions": [{"page_number": 3, "polygon": [{"x": 0.5394, "y": 2.5965}, {"x": 1.5591, "y": 2.5965}, {"x": 1.5591, "y": 2.743}, {"x": 0.5394, "y": 2.743}]}], "spans": [{"offset": 183, "length": 12}]}, {"kind": "content", "row_index": 3, "column_index": 1, "row_span": 1, "column_span": 1, "content": "Ronald", "bounding_regions": [{"page_number": 3, "polygon": [{"x": 1.5591, "y": 2.5965}, {"x": 2.802, "y": 2.5965}, {"x": 2.802, "y": 2.743}, {"x": 1.5591, "y": 2.743}]}], "spans": [{"offset": 196, "length": 6}]}, {"kind": "content", "row_index": 3, "column_index": 2, "row_span": 1, "column_span": 1, "content": "Race:", "bounding_regions": [{"page_number": 3, "polygon": [{"x": 2.802, "y": 2.5965}, {"x": 3.9631, "y": 2.5965}, {"x": 3.9631, "y": 2.743}, {"x": 2.802, "y": 2.743}]}], "spans": [{"offset": 203, "length": 5}]}, {"kind": "content", "row_index": 3, "column_index": 3, "row_span": 1, "column_span": 1, "content": "White", "bounding_regions": [{"page_number": 3, "polygon": [{"x": 3.9631, "y": 2.5965}, {"x": 4.685, "y": 2.5965}, {"x": 4.685, "y": 2.743}, {"x": 3.9631, "y": 2.743}]}], "spans": [{"offset": 209, "length": 5}]}, {"kind": "content", "row_index": 3, "column_index": 4, "row_span": 1, "column_span": 1, "content": "Sex:", "bounding_regions": [{"page_number": 3, "polygon": [{"x": 4.685, "y": 2.5965}, {"x": 5.34, "y": 2.5965}, {"x": 5.34, "y": 2.7356}, {"x": 4.685, "y": 2.743}]}], "spans": [{"offset": 215, "length": 4}]}, {"kind": "content", "row_index": 3, "column_index": 5, "row_span": 1, "column_span": 1, "content": "Male", "bounding_regions": [{"page_number": 3, "polygon": [{"x": 5.34, "y": 2.5965}, {"x": 6.3745, "y": 2.5892}, {"x": 6.3745, "y": 2.7356}, {"x": 5.34, "y": 2.7356}]}], "spans": [{"offset": 220, "length": 4}]}, {"kind": "content", "row_index": 4, "column_index": 0, "row_span": 1, "column_span": 1, "content": "Address: 19310\nPrimary Phone:", "bounding_regions": [{"page_number": 3, "polygon": [{"x": 0.5394, "y": 2.743}, {"x": 1.5591, "y": 2.743}, {"x": 1.5516, "y": 3.2848}, {"x": 0.5394, "y": 3.2848}]}], "spans": [{"offset": 225, "length": 14}, {"offset": 271, "length": 14}]}, {"kind": "content", "row_index": 4, "column_index": 1, "row_span": 1, "column_span": 1, "content": "MUSKOKA AVE CLEVELAND OH 44119\n(216)501-8124", "bounding_regions": [{"page_number": 3, "polygon": [{"x": 1.5591, "y": 2.743}, {"x": 2.802, "y": 2.743}, {"x": 2.8095, "y": 3.2848}, {"x": 1.5516, "y": 3.2848}]}], "spans": [{"offset": 240, "length": 30}, {"offset": 286, "length": 13}]}, {"kind": "content", "row_index": 4, "column_index": 2, "row_span": 1, "column_span": 1, "content": "Height: Eyes: SSN:", "bounding_regions": [{"page_number": 3, "polygon": [{"x": 2.802, "y": 2.743}, {"x": 3.9631, "y": 2.743}, {"x": 3.9631, "y": 3.2775}, {"x": 2.8095, "y": 3.2848}]}], "spans": [{"offset": 300, "length": 18}]}, {"kind": "content", "row_index": 4, "column_index": 3, "row_span": 1, "column_span": 1, "content": "5ft 11 in Blue", "bounding_regions": [{"page_number": 3, "polygon": [{"x": 3.9631, "y": 2.743}, {"x": 4.685, "y": 2.743}, {"x": 4.685, "y": 3.2775}, {"x": 3.9631, "y": 3.2775}]}], "spans": [{"offset": 319, "length": 14}]}, {"kind": "content", "row_index": 4, "column_index": 4, "row_span": 1, "column_span": 1, "content": "Weight: Hair: DVL #:", "bounding_regions": [{"page_number": 3, "polygon": [{"x": 4.685, "y": 2.743}, {"x": 5.34, "y": 2.7356}, {"x": 5.3326, "y": 3.2775}, {"x": 4.685, "y": 3.2775}]}], "spans": [{"offset": 334, "length": 20}]}, {"kind": "content", "row_index": 4, "column_index": 5, "row_span": 1, "column_span": 1, "content": "250.0 lbs. Blonde or Strawberry 1 - MTR V...", "bounding_regions": [{"page_number": 3, "polygon": [{"x": 5.34, "y": 2.7356}, {"x": 6.3745, "y": 2.7356}, {"x": 6.382, "y": 3.2775}, {"x": 5.3326, "y": 3.2775}]}], "spans": [{"offset": 355, "length": 44}]}, {"kind": "content", "row_index": 5, "column_index": 0, "row_span": 1, "column_span": 1, "content": "Resident Type:", "bounding_regions": [{"page_number": 3, "polygon": [{"x": 0.5394, "y": 3.2848}, {"x": 1.5516, "y": 3.2848}, {"x": 1.5516, "y": 3.4312}, {"x": 0.5394, "y": 3.4312}]}], "spans": [{"offset": 400, "length": 14}]}, {"kind": "content", "row_index": 5, "column_index": 1, "row_span": 1, "column_span": 1, "content": "City", "bounding_regions": [{"page_number": 3, "polygon": [{"x": 1.5516, "y": 3.2848}, {"x": 2.8095, "y": 3.2848}, {"x": 2.8095, "y": 3.4312}, {"x": 1.5516, "y": 3.4312}]}], "spans": [{"offset": 415, "length": 4}]}, {"kind": "content", "row_index": 5, "column_index": 2, "row_span": 1, "column_span": 1, "content": "Resident Status:", "bounding_regions": [{"page_number": 3, "polygon": [{"x": 2.8095, "y": 3.2848}, {"x": 3.9631, "y": 3.2775}, {"x": 3.9631, "y": 3.4312}, {"x": 2.8095, "y": 3.4312}]}], "spans": [{"offset": 420, "length": 16}]}, {"kind": "content", "row_index": 5, "column_index": 3, "row_span": 1, "column_span": 1, "content": "Resident", "bounding_regions": [{"page_number": 3, "polygon": [{"x": 3.9631, "y": 3.2775}, {"x": 4.685, "y": 3.2775}, {"x": 4.685, "y": 3.4312}, {"x": 3.9631, "y": 3.4312}]}], "spans": [{"offset": 437, "length": 8}]}, {"kind": "content", "row_index": 5, "column_index": 4, "row_span": 1, "column_span": 1, "content": "", "bounding_regions": [{"page_number": 3, "polygon": [{"x": 4.685, "y": 3.2775}, {"x": 5.3326, "y": 3.2775}, {"x": 5.3326, "y": 3.4312}, {"x": 4.685, "y": 3.4312}]}], "spans": []}, {"kind": "content", "row_index": 5, "column_index": 5, "row_span": 1, "column_span": 1, "content": "Statement Type:", "bounding_regions": [{"page_number": 3, "polygon": [{"x": 5.3326, "y": 3.2775}, {"x": 6.382, "y": 3.2775}, {"x": 6.382, "y": 3.4312}, {"x": 5.3326, "y": 3.4312}]}], "spans": [{"offset": 446, "length": 15}]}, {"kind": "content", "row_index": 6, "column_index": 0, "row_span": 1, "column_span": 1, "content": "Disposition:", "bounding_regions": [{"page_number": 3, "polygon": [{"x": 0.5394, "y": 3.4312}, {"x": 1.5516, "y": 3.4312}, {"x": 1.5442, "y": 3.5996}, {"x": 0.5394, "y": 3.5996}]}], "spans": [{"offset": 462, "length": 12}]}, {"kind": "content", "row_index": 6, "column_index": 1, "row_span": 1, "column_span": 1, "content": "", "bounding_regions": [{"page_number": 3, "polygon": [{"x": 1.5516, "y": 3.4312}, {"x": 2.8095, "y": 3.4312}, {"x": 2.8095, "y": 3.5996}, {"x": 1.5442, "y": 3.5996}]}], "spans": []}, {"kind": "content", "row_index": 6, "column_index": 2, "row_span": 1, "column_span": 1, "content": "Date:", "bounding_regions": [{"page_number": 3, "polygon": [{"x": 2.8095, "y": 3.4312}, {"x": 3.9631, "y": 3.4312}, {"x": 3.9631, "y": 3.5996}, {"x": 2.8095, "y": 3.5996}]}], "spans": [{"offset": 475, "length": 5}]}, {"kind": "content", "row_index": 6, "column_index": 3, "row_span": 1, "column_span": 1, "content": "", "bounding_regions": [{"page_number": 3, "polygon": [{"x": 3.9631, "y": 3.4312}, {"x": 4.685, "y": 3.4312}, {"x": 4.685, "y": 3.5996}, {"x": 3.9631, "y": 3.5996}]}], "spans": []}, {"kind": "content", "row_index": 6, "column_index": 4, "row_span": 1, "column_span": 1, "content": "", "bounding_regions": [{"page_number": 3, "polygon": [{"x": 4.685, "y": 3.4312}, {"x": 5.3326, "y": 3.4312}, {"x": 5.3326, "y": 3.5996}, {"x": 4.685, "y": 3.5996}]}], "spans": []}, {"kind": "content", "row_index": 6, "column_index": 5, "row_span": 1, "column_span": 1, "content": "Custody Status:", "bounding_regions": [{"page_number": 3, "polygon": [{"x": 5.3326, "y": 3.4312}, {"x": 6.382, "y": 3.4312}, {"x": 6.3894, "y": 3.5996}, {"x": 5.3326, "y": 3.5996}]}], "spans": [{"offset": 481, "length": 15}]}, {"kind": "content", "row_index": 7, "column_index": 0, "row_span": 1, "column_span": 1, "content": "Related Offenses", "bounding_regions": [{"page_number": 3, "polygon": [{"x": 0.5394, "y": 3.5996}, {"x": 1.5442, "y": 3.5996}, {"x": 1.5442, "y": 3.7827}, {"x": 0.5394, "y": 3.7827}]}], "spans": [{"offset": 497, "length": 16}]}, {"kind": "content", "row_index": 7, "column_index": 1, "row_span": 1, "column_span": 1, "content": "", "bounding_regions": [{"page_number": 3, "polygon": [{"x": 1.5442, "y": 3.5996}, {"x": 2.8095, "y": 3.5996}, {"x": 2.8095, "y": 3.7827}, {"x": 1.5442, "y": 3.7827}]}], "spans": []}, {"kind": "content", "row_index": 7, "column_index": 2, "row_span": 1, "column_span": 1, "content": "", "bounding_regions": [{"page_number": 3, "polygon": [{"x": 2.8095, "y": 3.5996}, {"x": 3.9631, "y": 3.5996}, {"x": 3.9631, "y": 3.7827}, {"x": 2.8095, "y": 3.7827}]}], "spans": []}, {"kind": "content", "row_index": 7, "column_index": 3, "row_span": 1, "column_span": 1, "content": "", "bounding_regions": [{"page_number": 3, "polygon": [{"x": 3.9631, "y": 3.5996}, {"x": 4.685, "y": 3.5996}, {"x": 4.685, "y": 3.79}, {"x": 3.9631, "y": 3.7827}]}], "spans": []}, {"kind": "content", "row_index": 7, "column_index": 4, "row_span": 1, "column_span": 1, "content": "", "bounding_regions": [{"page_number": 3, "polygon": [{"x": 4.685, "y": 3.5996}, {"x": 5.3326, "y": 3.5996}, {"x": 5.3326, "y": 3.79}, {"x": 4.685, "y": 3.79}]}], "spans": []}, {"kind": "content", "row_index": 7, "column_index": 5, "row_span": 1, "column_span": 1, "content": "", "bounding_regions": [{"page_number": 3, "polygon": [{"x": 5.3326, "y": 3.5996}, {"x": 6.3894, "y": 3.5996}, {"x": 6.3894, "y": 3.79}, {"x": 5.3326, "y": 3.79}]}], "spans": []}, {"kind": "content", "row_index": 8, "column_index": 0, "row_span": 1, "column_span": 1, "content": "Group/ORI", "bounding_regions": [{"page_number": 3, "polygon": [{"x": 0.5394, "y": 3.7827}, {"x": 1.5442, "y": 3.7827}, {"x": 1.5442, "y": 4.0097}, {"x": 0.5394, "y": 4.0097}]}], "spans": [{"offset": 514, "length": 9}]}, {"kind": "content", "row_index": 8, "column_index": 1, "row_span": 1, "column_span": 1, "content": "Crime Code", "bounding_regions": [{"page_number": 3, "polygon": [{"x": 1.5442, "y": 3.7827}, {"x": 2.8095, "y": 3.7827}, {"x": 2.8095, "y": 4.0097}, {"x": 1.5442, "y": 4.0097}]}], "spans": [{"offset": 524, "length": 10}]}, {"kind": "content", "row_index": 8, "column_index": 2, "row_span": 1, "column_span": 1, "content": "Statute", "bounding_regions": [{"page_number": 3, "polygon": [{"x": 2.8095, "y": 3.7827}, {"x": 3.9631, "y": 3.7827}, {"x": 3.9631, "y": 4.0024}, {"x": 2.8095, "y": 4.0097}]}], "spans": [{"offset": 535, "length": 7}]}, {"kind": "content", "row_index": 8, "column_index": 3, "row_span": 1, "column_span": 1, "content": "", "bounding_regions": [{"page_number": 3, "polygon": [{"x": 3.9631, "y": 3.7827}, {"x": 4.685, "y": 3.79}, {"x": 4.685, "y": 4.0024}, {"x": 3.9631, "y": 4.0024}]}], "spans": []}, {"kind": "content", "row_index": 8, "column_index": 4, "row_span": 1, "column_span": 1, "content": "", "bounding_regions": [{"page_number": 3, "polygon": [{"x": 4.685, "y": 3.79}, {"x": 5.3326, "y": 3.79}, {"x": 5.3326, "y": 4.0024}, {"x": 4.685, "y": 4.0024}]}], "spans": []}, {"kind": "content", "row_index": 8, "column_index": 5, "row_span": 1, "column_span": 1, "content": "Description", "bounding_regions": [{"page_number": 3, "polygon": [{"x": 5.3326, "y": 3.79}, {"x": 6.3894, "y": 3.79}, {"x": 6.3894, "y": 4.0024}, {"x": 5.3326, "y": 4.0024}]}], "spans": [{"offset": 543, "length": 11}]}, {"kind": "content", "row_index": 9, "column_index": 0, "row_span": 1, "column_span": 1, "content": "OHCLP0000", "bounding_regions": [{"page_number": 3, "polygon": [{"x": 0.5394, "y": 4.0097}, {"x": 1.5442, "y": 4.0097}, {"x": 1.5368, "y": 4.2733}, {"x": 0.5394, "y": 4.2733}]}], "spans": [{"offset": 555, "length": 9}]}, {"kind": "content", "row_index": 9, "column_index": 1, "row_span": 1, "column_span": 1, "content": "27120", "bounding_regions": [{"page_number": 3, "polygon": [{"x": 1.5442, "y": 4.0097}, {"x": 2.8095, "y": 4.0097}, {"x": 2.8095, "y": 4.266}, {"x": 1.5368, "y": 4.2733}]}], "spans": [{"offset": 565, "length": 5}]}, {"kind": "content", "row_index": 9, "column_index": 2, "row_span": 1, "column_span": 1, "content": "623.16", "bounding_regions": [{"page_number": 3, "polygon": [{"x": 2.8095, "y": 4.0097}, {"x": 3.9631, "y": 4.0024}, {"x": 3.9631, "y": 4.2733}, {"x": 2.8095, "y": 4.266}]}], "spans": [{"offset": 571, "length": 6}]}, {"kind": "content", "row_index": 9, "column_index": 3, "row_span": 1, "column_span": 1, "content": "", "bounding_regions": [{"page_number": 3, "polygon": [{"x": 3.9631, "y": 4.0024}, {"x": 4.685, "y": 4.0024}, {"x": 4.685, "y": 4.2733}, {"x": 3.9631, "y": 4.2733}]}], "spans": []}, {"kind": "content", "row_index": 9, "column_index": 4, "row_span": 1, "column_span": 1, "content": "", "bounding_regions": [{"page_number": 3, "polygon": [{"x": 4.685, "y": 4.0024}, {"x": 5.3326, "y": 4.0024}, {"x": 5.3326, "y": 4.2733}, {"x": 4.685, "y": 4.2733}]}], "spans": []}, {"kind": "content", "row_index": 9, "column_index": 5, "row_span": 1, "column_span": 1, "content": "No Person Shall Violate,,,,,\nRace", "bounding_regions": [{"page_number": 3, "polygon": [{"x": 5.3326, "y": 4.0024}, {"x": 6.3894, "y": 4.0024}, {"x": 6.3969, "y": 4.2806}, {"x": 5.3326, "y": 4.2733}]}], "spans": [{"offset": 578, "length": 28}, {"offset": 624, "length": 4}]}], "bounding_regions": [{"page_number": 3, "polygon": [{"x": 0.5822, "y": 1.627}, {"x": 7.7602, "y": 1.6669}, {"x": 7.7554, "y": 4.2906}, {"x": 0.575, "y": 4.251}]}], "spans": [{"offset": 36, "length": 203}, {"offset": 271, "length": 14}, {"offset": 240, "length": 30}, {"offset": 286, "length": 320}, {"offset": 624, "length": 4}]}, {"row_count": 5, "column_count": 4, "cells": [{"kind": "columnHeader", "row_index": 0, "column_index": 0, "row_span": 1, "column_span": 2, "content": "No. Type", "bounding_regions": [{"page_number": 3, "polygon": [{"x": 0.5699, "y": 4.8966}, {"x": 2.3021, "y": 4.8966}, {"x": 2.3021, "y": 5.1101}, {"x": 0.5624, "y": 5.1101}]}], "spans": [{"offset": 768, "length": 8}]}, {"kind": "columnHeader", "row_index": 0, "column_index": 2, "row_span": 1, "column_span": 1, "content": "Name", "bounding_regions": [{"page_number": 3, "polygon": [{"x": 2.3021, "y": 4.8966}, {"x": 4.9192, "y": 4.8966}, {"x": 4.9192, "y": 5.1101}, {"x": 2.3021, "y": 5.1101}]}], "spans": [{"offset": 777, "length": 4}]}, {"kind": "columnHeader", "row_index": 0, "column_index": 3, "row_span": 1, "column_span": 1, "content": "Relationship", "bounding_regions": [{"page_number": 3, "polygon": [{"x": 4.9192, "y": 4.8966}, {"x": 7.5439, "y": 4.8966}, {"x": 7.5439, "y": 5.1101}, {"x": 4.9192, "y": 5.1101}]}], "spans": [{"offset": 782, "length": 12}]}, {"kind": "content", "row_index": 1, "column_index": 0, "row_span": 1, "column_span": 2, "content": "1 Suspect", "bounding_regions": [{"page_number": 3, "polygon": [{"x": 0.5624, "y": 5.1101}, {"x": 2.3021, "y": 5.1101}, {"x": 2.3097, "y": 5.3236}, {"x": 0.5548, "y": 5.3309}]}], "spans": [{"offset": 795, "length": 9}]}, {"kind": "content", "row_index": 1, "column_index": 2, "row_span": 1, "column_span": 1, "content": "Payne,Ronald", "bounding_regions": [{"page_number": 3, "polygon": [{"x": 2.3021, "y": 5.1101}, {"x": 4.9192, "y": 5.1101}, {"x": 4.9268, "y": 5.3309}, {"x": 2.3097, "y": 5.3236}]}], "spans": [{"offset": 805, "length": 12}]}, {"kind": "content", "row_index": 1, "column_index": 3, "row_span": 1, "column_span": 1, "content": "Neighbor", "bounding_regions": [{"page_number": 3, "polygon": [{"x": 4.9192, "y": 5.1101}, {"x": 7.5439, "y": 5.1101}, {"x": 7.5439, "y": 5.3383}, {"x": 4.9268, "y": 5.3309}]}], "spans": [{"offset": 818, "length": 8}]}, {"kind": "content", "row_index": 2, "column_index": 0, "row_span": 1, "column_span": 2, "content": "Transported By:", "bounding_regions": [{"page_number": 3, "polygon": [{"x": 0.5548, "y": 5.3309}, {"x": 2.3097, "y": 5.3236}, {"x": 2.3097, "y": 5.5444}, {"x": 0.5548, "y": 5.5517}]}], "spans": [{"offset": 827, "length": 15}]}, {"kind": "content", "row_index": 2, "column_index": 2, "row_span": 1, "column_span": 1, "content": "Extent of Injury:", "bounding_regions": [{"page_number": 3, "polygon": [{"x": 2.3097, "y": 5.3236}, {"x": 4.9268, "y": 5.3309}, {"x": 4.9268, "y": 5.5444}, {"x": 2.3097, "y": 5.5444}]}], "spans": [{"offset": 843, "length": 17}]}, {"kind": "content", "row_index": 2, "column_index": 3, "row_span": 1, "column_span": 1, "content": "Hospital:", "bounding_regions": [{"page_number": 3, "polygon": [{"x": 4.9268, "y": 5.3309}, {"x": 7.5439, "y": 5.3383}, {"x": 7.5364, "y": 5.5517}, {"x": 4.9268, "y": 5.5444}]}], "spans": [{"offset": 861, "length": 9}]}, {"kind": "content", "row_index": 3, "column_index": 0, "row_span": 1, "column_span": 2, "content": "Domestic Violence: Condition:", "bounding_regions": [{"page_number": 3, "polygon": [{"x": 0.5548, "y": 5.5517}, {"x": 2.3097, "y": 5.5444}, {"x": 2.3097, "y": 5.8609}, {"x": 0.5472, "y": 5.8682}]}], "spans": [{"offset": 871, "length": 29}]}, {"kind": "content", "row_index": 3, "column_index": 2, "row_span": 1, "column_span": 1, "content": "Domestic Violence Referrals: Medical Treatment:", "bounding_regions": [{"page_number": 3, "polygon": [{"x": 2.3097, "y": 5.5444}, {"x": 4.9268, "y": 5.5444}, {"x": 4.9268, "y": 5.8682}, {"x": 2.3097, "y": 5.8609}]}], "spans": [{"offset": 901, "length": 47}]}, {"kind": "content", "row_index": 3, "column_index": 3, "row_span": 1, "column_span": 1, "content": "Federal Agencies Involved:", "bounding_regions": [{"page_number": 3, "polygon": [{"x": 4.9268, "y": 5.5444}, {"x": 7.5364, "y": 5.5517}, {"x": 7.5364, "y": 5.8756}, {"x": 4.9268, "y": 5.8682}]}], "spans": [{"offset": 949, "length": 26}]}, {"kind": "content", "row_index": 4, "column_index": 0, "row_span": 1, "column_span": 2, "content": "Injury Types", "bounding_regions": [{"page_number": 3, "polygon": [{"x": 0.5472, "y": 5.8682}, {"x": 2.3097, "y": 5.8609}, {"x": 2.3097, "y": 6.0817}, {"x": 0.5397, "y": 6.0743}]}], "spans": [{"offset": 976, "length": 12}]}, {"kind": "content", "row_index": 4, "column_index": 2, "row_span": 1, "column_span": 1, "content": "Modus", "bounding_regions": [{"page_number": 3, "polygon": [{"x": 2.3097, "y": 5.8609}, {"x": 4.9268, "y": 5.8682}, {"x": 4.9268, "y": 6.0669}, {"x": 2.3097, "y": 6.0817}]}], "spans": [{"offset": 989, "length": 5}]}, {"kind": "content", "row_index": 4, "column_index": 3, "row_span": 1, "column_span": 1, "content": "Operandi", "bounding_regions": [{"page_number": 3, "polygon": [{"x": 4.9268, "y": 5.8682}, {"x": 7.5364, "y": 5.8756}, {"x": 7.5364, "y": 6.0743}, {"x": 4.9268, "y": 6.0669}]}], "spans": [{"offset": 995, "length": 8}]}], "bounding_regions": [{"page_number": 3, "polygon": [{"x": 0.5805, "y": 4.8896}, {"x": 7.886, "y": 4.8953}, {"x": 7.8872, "y": 5.9233}, {"x": 0.5811, "y": 5.9188}]}], "spans": [{"offset": 768, "length": 235}]}], "key_value_pairs": [], "styles": [], "documents": [{"doc_type": "bc2-narrative", "bounding_regions": [{"page_number": 3, "polygon": [{"x": 0.0, "y": 0.0}, {"x": 8.5, "y": 0.0}, {"x": 8.5, "y": 11.0}, {"x": 0.0, "y": 11.0}]}], "spans": [{"offset": 0, "length": 1188}], "fields": {"narrative": {"value_type": "string", "value": null, "content": null, "bounding_regions": [], "spans": [], "confidence": 0.732}}, "confidence": 0.876}]}
